Workbook

Sheet 📌 COVER
A1: BNP PARIBAS SA — THREE-YEAR FINANCIAL ANALYSIS
A2: FY 2022 | FY 2023 | FY 2024
A3: IFRS financial analysis | ECB SSM regulated institution | All monetary figures in € millions unless stated
A6: ANALYST INFORMATION
A8: Analyst Name: | C8: Joy Lorna
A9: Role Target: | C9: Financial Analyst — Luxembourg Banking / Big 4
A10: Analysis Date: | C10: =DATE(2026,8,25) -> 46259
A11: Workbook Version: | C11: v2.2
A13: ENTITY OVERVIEW
A15: Legal Entity: | C15: BNP Paribas SA
A16: Headquarters: | C16: 16 Boulevard des Italiens, 75009 Paris, France
A17: Listed: | C17: Euronext Paris — Ticker: BNP (CAC 40)
A18: ISIN: | C18: FR0000131104
A20: Business Model: | C20: Universal bank — Retail, Corporate & Institutional
C21: Banking (CIB), Asset & Wealth Management
A22: Supervision: | C22: ECB SSM (Significant Institution under SSM)
C23: SREP annual cycle, G-SIB designation
A27: ANALYSIS SCOPE
A29: Period: | C29: FY 2022 | FY 2023 | FY 2024
A30: Reporting Standard: | C30: IFRS (as adopted by EU, including IFRS 9 and IFRS 17 where applicable)
A31: Currency: | C31: EUR (€ millions) unless stated
A32: Statements in Scope: | C32: Income Statement, Balance Sheet, Cash Flow, Analyst Note
A33: Ratio Families: | C33: 5 — Profitability, Liquidity, Capital, Asset Quality, Efficiency
A34: Regulatory Context: | C34: ECB SSM / SREP, CRR3 / CRD VI, IFRS 9 / IFRS 17, Pillar 3
A35: Data Preparation: | C35: Manual extraction from official BNP PDFs; standardised and source-verified in Excel. FY2022 analytical figures use BNP Paribas’ IFRS 17/9 restated comparative basis where applicable and are presented consistently with FY2023–FY2024. Reported-versus-restated differences are documented in IFRS17_RESTATEMENT_NOTE.
A37: DATASET SOURCES — OFFICIAL BNP PARIBAS PDF DOCUMENTS
A39: FY 2022
A40: 1 | C40: Consolidated Financial Statements — Year ended 31 December 2022 (annual, audited) — https://invest.bnpparibas/document/4q22-consolidated-financial-statements-annual-audited
A41: 2 | C41: Results as at 31 December 2022 — Press release — https://invest.bnpparibas/document/4q22-pr
A42: 3 | C42: 2022 Full-Year Results — Slides — https://invest.bnpparibas/document/4q22-slides
A43: 4 | C43: Universal Registration Document and Annual Financial Report 2022 — includes Pillar 3 risk reports — https://invest.bnpparibas/document/universal-registration-document-2022
A44: FY 2023
A45: 1 | C45: Consolidated Financial Statements — Year ended 31 December 2023 (annual, audited) — https://invest.bnpparibas/document/4q23-consolidated-financial-statements-annual-audited
A46: 2 | C46: Results as at 31 December 2023 — Press release — https://invest.bnpparibas/document/4q23-pr
A47: 3 | C47: 2023 Full-Year Results — Slides — https://invest.bnpparibas/document/4q23-slides
A48: 4 | C48: Universal Registration Document and Annual Financial Report 2023 — includes Pillar 3 risk reports — https://invest.bnpparibas/document/universal-registration-document-annual-financial-report-2023-pdf
A49: FY 2024
A50: 1 | C50: Consolidated Financial Statements — Year ended 31 December 2024 (unaudited figures) — https://invest.bnpparibas/document/4q24-cfsu
A51: 2 | C51: Fourth-Quarter and Full-Year 2024 Results — Press release — https://invest.bnpparibas/document/4q24-pr
A52: 3 | C52: Fourth-Quarter and 2024 Full-Year Results — Slides — https://invest.bnpparibas/document/4q24-slides
A53: 4 | C53: Universal Registration Document and Annual Financial Report 2024 — includes Pillar 3 risk reports and audited figures — https://invest.bnpparibas/document/universal-registration-document-annual-financial-report-2024-pdf
A55: REGULATORY FRAMEWORK
A57: ✓ ECB SSM (Single Supervisory Mechanism) — BNP Paribas is a significant institution
A58: ✓ SREP (Supervisory Review and Evaluation Process) — annual supervisory decision
A59: ✓ CRD VI / CRR3 — capital and liquidity requirements
A60: ✓ IFRS 9 — expected credit loss (ECL) model for provisions
A61: ✓ IFRS 17 — insurance accounting and FY2022 restated comparative presentation
A63: ✓ Pillar 3 — regulatory capital and risk disclosures
A64: ✓ TLAC / MREL — total loss-absorbing capacity requirements for a G-SIB
A66: KEY METRICS COVERED IN THIS WORKBOOK
A68: Profitability: | C68: ROE, ROTE, ROA, NIM, NII, CIR, EPS
A69: Liquidity: | C69: LCR (>100% minimum), NSFR, Loan-to-Deposit Ratio, HQLA
A70: Capital: | C70: CET1, Tier 1, Total Capital, Leverage Ratio, RWA
A71: Asset Quality: | C71: NPL Ratio, Stage 1/2/3 ECL, Coverage Ratio, Cost of Risk
A72: Efficiency: | C72: CIR, Operating Leverage
A74: DISCLAIMER
A76: This workbook is prepared for portfolio demonstration and interview preparation purposes only. All figures should be verified against BNP Paribas official published disclosures. It is not investment advice.

Sheet 🔎WORKBOOK SHEET MAP
A1: BNP PARIBAS — WORKBOOK SHEET MAP
A2: Navigation guide for the FY 2022–FY 2024 financial analysis workbook
A3: 24 worksheets | Financial statements, analyst note, ratios, analytical bridges, charts, sources, controls, and audit documentation
A5: WORKBOOK CONTENTS
A6: TAB # | B6: WORKSHEET | C6: PURPOSE
A7: 1 | B7: 📌 COVER | C7: Workbook identity, scope, sources, and disclaimer
A8: 2 | B8: 🔎WORKBOOK SHEET MAP | C8: Navigation index for every worksheet
A9: 3 | B9: 📊 EXECUTIVE_SUMMARY | C9: Executive KPI scorecard and key findings
A10: 4 | B10: 📝 ANALYST_NOTE | C10: PDF-ready performance narrative, risk flags, and forward outlook
A11: 5 | B11: 📄 INCOME_STATEMENT | C11: Three-year income statement and key metrics
A12: 6 | B12: 🏦 BALANCE_SHEET | C12: Three-year assets, liabilities, equity, and reconciliation
A13: 7 | B13: 💰 CASH_FLOW | C13: Three-year cash-flow statement and cash review
A14: 8 | B14: 🧮VARIANCE BRIDGE | C14: Year-on-year earnings attribution and reconciliation
A15: 9 | B15: 📈 RATIOS_PROFITABILITY | C15: Profitability and return ratios
A16: 10 | B16: 📈 RATIOS_LIQUIDITY | C16: Liquidity and funding ratios
A17: 11 | B17: 📈 RATIOS_CAPITAL | C17: Regulatory capital and RWA analysis
A18: 12 | B18: 📈 RATIOS_ASSET_QUALITY | C18: Credit quality and IFRS 9 analysis
... A30: 24 | B30: ANALYTICAL_INPUTS | C30: Visible sourced denominator inputs for profitability ratios
A32: Use this page as the workbook table of contents.

Sheet 📊 EXECUTIVE_SUMMARY
A1: BNP PARIBAS SA — EXECUTIVE KPI SCORECARD
A2: FY 2022–FY 2024 | IFRS | ECB SSM regulated institution
A3: All monetary values in €M unless stated | Live-linked to the workbook’s financial statements and ratio schedules
A5: STORY IN BRIEF
A6: Net income attributable to equity holders increased from €9,848M in restated FY2022 to €11,688M in FY2024, an 8.9% two-year CAGR. FY2024 combined 6.4% NBI growth with lower operating expenses; standard Cost of Risk increased slightly, while other net risk losses declined substantially. Capital and liquidity ratios remained above the regulatory or analytical comparison levels explicitly assessed in this workbook, while NPLs improved to 1.6%.
A10: METRIC | B10: FY 2022 Restated | C10: FY 2023 | D10: FY 2024 | E10: TREND | F10: SIGNAL
A11: EARNINGS & REVENUE
A12: Net Banking Income (€M) | B12: ='📄 INCOME_STATEMENT'!B15 -> 45430 | C12: ='📄 INCOME_STATEMENT'!C15 -> 45874 | D12: ='📄 INCOME_STATEMENT'!D15 -> 48831 | E12: ↗ | F12: Strong revenue growth
A13: Net Interest Income (€M) | B13: ='📄 INCOME_STATEMENT'!B10 -> 20933 | C13: ='📄 INCOME_STATEMENT'!C10 -> 19058 | D13: ='📄 INCOME_STATEMENT'!D10 -> 19524 | E13: ↘↗ | F13: Rate-cycle pressure
A14: Fee & Commission Income (€M) | B14: ='📄 INCOME_STATEMENT'!B11 -> 10165 | C14: ='📄 INCOME_STATEMENT'!C11 -> 9821 | D14: ='📄 INCOME_STATEMENT'!D11 -> 10701 | E14: ↘↗ | F14: Resilient recovery
A15: Operating Expenses (€M) | B15: ='📄 INCOME_STATEMENT'!B22 -> 29864 | C15: ='📄 INCOME_STATEMENT'!C22 -> 30956 | D15: ='📄 INCOME_STATEMENT'!D22 -> 30193 | E15: ↗↘ | F15: Costs eased in FY2024
A16: Cost of Risk (€M) | B16: ='📄 INCOME_STATEMENT'!B27 -> 3003 | C16: ='📄 INCOME_STATEMENT'!C27 -> 2907 | D16: ='📄 INCOME_STATEMENT'!D27 -> 2999 | E16: ↗↘ | F16: Standard Cost of Risk; +3.2% in FY2024
A17: Other net risk losses (€M) | B17: ='📄 INCOME_STATEMENT'!B28 -> 0 | C17: ='📄 INCOME_STATEMENT'!C28 -> 775 | D17: ='📄 INCOME_STATEMENT'!D28 -> 202 | E17: ↘ | F17: Declined substantially in FY2024
A18: Net Income — Equity Holders (€M) | B18: ='📄 INCOME_STATEMENT'!B44 -> 9848 | C18: ='📄 INCOME_STATEMENT'!C44 -> 10975 | D18: ='📄 INCOME_STATEMENT'!D44 -> 11688 | E18: ↗ | F18: Strong earnings growth
A20: PROFITABILITY & RETURNS
A21: Return on Equity (ROE) | B21: ='📈 RATIOS_PROFITABILITY'!C8 -> 0.082367652 | C21: ='📈 RATIOS_PROFITABILITY'!D8 -> 0.089599517 | D21: ='📈 RATIOS_PROFITABILITY'!E8 -> 0.092806467 | E21: ↗ | F21: Improving; below EU average
A22: Return on Tangible Equity (ROTE) | B22: ='📈 RATIOS_PROFITABILITY'!C9 -> 0.089017848 | C22: ='📈 RATIOS_PROFITABILITY'!D9 -> 0.097036304 | D22: ='📈 RATIOS_PROFITABILITY'!E9 -> 0.10065189 | E22: ↗ | F22: Improving; no external target assessed
A23: Return on Assets (ROA) | B23: ='📈 RATIOS_PROFITABILITY'!C10 -> 0.0037174946 | C23: ='📈 RATIOS_PROFITABILITY'!D10 -> 0.004176778 | D23: ='📈 RATIOS_PROFITABILITY'!E10 -> 0.0044135581 | E23: ↗ | F23: Within EU bank range
A24: Net Interest Margin (NIM) | B24: ='📈 RATIOS_PROFITABILITY'!C11 -> 0.020698128 | C24: ='📈 RATIOS_PROFITABILITY'!D11 -> 0.018198155 | D24: ='📈 RATIOS_PROFITABILITY'!E11 -> 0.01771155 | E24: ↘ | F24: At upper end of EU range
A25: Net Income Margin | B25: ='📈 RATIOS_PROFITABILITY'!C14 -> 0.21677306 | C25: ='📈 RATIOS_PROFITABILITY'!D14 -> 0.23924227 | D25: ='📈 RATIOS_PROFITABILITY'!E14 -> 0.23935615 | E25: ↗ | F25: Stable near 24%
A26: Earnings per Share (€) | B26: ='📈 RATIOS_PROFITABILITY'!C15 -> 7.52 | C26: ='📈 RATIOS_PROFITABILITY'!D15 -> 8.58 | D26: ='📈 RATIOS_PROFITABILITY'!E15 -> 9.57 | E26: ↗ | F26: Strong EPS growth
A28: CAPITAL & LIQUIDITY
A29: CET1 Ratio | B29: ='📈 RATIOS_CAPITAL'!C8 -> 0.1233 | C29: ='📈 RATIOS_CAPITAL'!D8 -> 0.132 | D29: ='📈 RATIOS_CAPITAL'!E8 -> 0.1287 | E29: ↗↘ | F29: Regulatory comparison only; no SREP threshold asserted
A30: Tier 1 Ratio | B30: ='📈 RATIOS_CAPITAL'!C9 -> 0.1389 | C30: ='📈 RATIOS_CAPITAL'!D9 -> 0.1528 | D30: ='📈 RATIOS_CAPITAL'!E9 -> 0.1493 | E30: ↗↘ | F30: Above stated base reference
A31: Total Capital Ratio | B31: ='📈 RATIOS_CAPITAL'!C10 -> 0.1619 | C31: ='📈 RATIOS_CAPITAL'!D10 -> 0.173 | D31: ='📈 RATIOS_CAPITAL'!E10 -> 0.1713 | E31: ↗↘ | F31: Above stated base reference
A32: Leverage Ratio | B32: ='📈 RATIOS_CAPITAL'!C11 -> 0.0436 | C32: ='📈 RATIOS_CAPITAL'!D11 -> 0.0458 | D32: ='📈 RATIOS_CAPITAL'!E11 -> 0.0462 | E32: ↗ | F32: Above 3% base reference
A33: Risk-Weighted Assets (€M) | B33: ='📈 RATIOS_CAPITAL'!B21 -> 744851 | C33: ='📈 RATIOS_CAPITAL'!C21 -> 703694 | D33: ='📈 RATIOS_CAPITAL'!D21 -> 762247 | E33: ↘↗ | F33: Managed capital intensity
A34: Liquidity Coverage Ratio (LCR) | B34: ='📈 RATIOS_LIQUIDITY'!C8 -> 1.29 | C34: ='📈 RATIOS_LIQUIDITY'!D8 -> 1.48 | D34: ='📈 RATIOS_LIQUIDITY'!E8 -> 1.37 | E34: ↗↘ | F34: Above 100% minimum
A35: Net Stable Funding Ratio (NSFR) | B35: ='📈 RATIOS_LIQUIDITY'!C9 -> 1.1505 | C35: ='📈 RATIOS_LIQUIDITY'!D9 -> 1.1592 | D35: ='📈 RATIOS_LIQUIDITY'!E9 -> 1.1175 | E35: → | F35: Above 100% minimum
A36: Loan-to-Deposit Ratio | B36: ='📈 RATIOS_LIQUIDITY'!C11 -> 0.85017102 | C36: ='📈 RATIOS_LIQUIDITY'!D11 -> 0.86915267 | D36: ='📈 RATIOS_LIQUIDITY'!E11 -> 0.86982163 | E36: → | F36: Deposits exceed customer loans
A38: ASSET QUALITY & EFFICIENCY
A39: NPL Ratio | B39: ='📈 RATIOS_ASSET_QUALITY'!C8 -> 0.017 | C39: ='📈 RATIOS_ASSET_QUALITY'!D8 -> 0.017 | D39: ='📈 RATIOS_ASSET_QUALITY'!E8 -> 0.016 | E39: ↘ | F39: Better than EU average
A40: Coverage Ratio | B40: ='📈 RATIOS_ASSET_QUALITY'!C9 -> 0.725 | C40: ='📈 RATIOS_ASSET_QUALITY'!D9 -> 0.717 | D40: ='📈 RATIOS_ASSET_QUALITY'!E9 -> 0.697 | E40: ↘ | F40: Adequate; declining buffer
A41: Cost of Risk (bps) | B41: ='📈 RATIOS_ASSET_QUALITY'!C11 -> 31 | C41: ='📈 RATIOS_ASSET_QUALITY'!D11 -> 32 | D41: ='📈 RATIOS_ASSET_QUALITY'!E11 -> 33 | E41: ↗ | F41: Below ECB Q2 2024 sector reference
A42: Stage 1 ECL (€M) | B42: ='📈 RATIOS_ASSET_QUALITY'!C12 -> 2035 | C42: ='📈 RATIOS_ASSET_QUALITY'!D12 -> 1938 | D42: ='📈 RATIOS_ASSET_QUALITY'!E12 -> 1785 | E42: ↘ | F42: Lower performing ECL
A43: Stage 2 ECL (€M) | B43: ='📈 RATIOS_ASSET_QUALITY'!C13 -> 2860 | C43: ='📈 RATIOS_ASSET_QUALITY'!D13 -> 2416 | D43: ='📈 RATIOS_ASSET_QUALITY'!E13 -> 1939 | E43: ↘ | F43: Lower lifetime ECL
A44: Stage 3 Allowance (€M) | B44: ='📈 RATIOS_ASSET_QUALITY'!C14 -> 13616 | C44: ='📈 RATIOS_ASSET_QUALITY'!D14 -> 13361 | D44: ='📈 RATIOS_ASSET_QUALITY'!E14 -> 13457 | E44: → | F44: Stable doubtful allowance
A45: Cost-to-Income Ratio (CIR) | B45: ='📈 RATIOS_EFFICIENCY'!C8 -> 0.65736298 | C45: ='📈 RATIOS_EFFICIENCY'!D8 -> 0.6748049 | D45: ='📈 RATIOS_EFFICIENCY'!E8 -> 0.61831623 | E45: ↗↘ | F45: Below 66% analytical comparison
A46: Operating Leverage (pp) | B46: ="n/a" -> n/a | C46: ='📈 RATIOS_EFFICIENCY'!D12 -> -2.6792487 | D46: ='📈 RATIOS_EFFICIENCY'!E12 -> 8.9107058 | E46: ↗ | F46: Positive in FY2024
A49: KEY FINDINGS
A50: 1 | B50: Earnings | C50: ="Net income reached €"&TEXT(D18,"#,##0")&"M in FY2024, up "&TEXT(D18/B18-1,"0.0%")&" from restated FY2022." -> Net income reached €11,688M in FY2024, up 18.7% from restated FY2022.
A51: 2 | B51: Efficiency | C51: CIR improved to 61.8% in FY2024 from 67.5% in FY2023, moving below the 66% analytical comparison.
A52: 3 | B52: Capital | C52: CET1 closed FY2024 at 12.87%. Regulatory reference levels are used for analytical comparison only; this workbook does not assert a BNP-specific SREP threshold.
A53: 4 | B53: Liquidity | C53: LCR and NSFR remained above 100% in every year; FY2024 closed at 137% and 111.75%.
A54: 5 | B54: Credit quality | C54: NPL improved to 1.6%, but coverage declined to 69.7%.
A57: MANAGEMENT TAKEAWAY
A58: BNP Paribas exited FY2024 with stronger earnings, improved efficiency, and sound liquidity. Reported capital ratios remained above the stated comparison levels used in this workbook. The main watchpoints are NIM compression, returns below stronger European benchmarks, and the gradual decline in NPL coverage.

Sheet 📝 ANALYST_NOTE
A1: BNP PARIBAS SA — FINANCIAL ANALYSIS NOTE
A2: FY 2022–FY 2024 | Analyst-style performance, risk, and outlook assessment
A3: Prepared by Joy Lorna | Portfolio demonstration | All monetary values in €M unless stated
A5: EXECUTIVE ASSESSMENT
A6: BNP Paribas delivered improving earnings and returns over FY2022–FY2024. Net income attributable to equity holders rose from €9,848M on the restated FY2022 basis to €11,688M in FY2024, an 8.9% two-year CAGR, while CIR improved to 61.83%. CET1 was 12.87%, LCR 137%, and NSFR 111.75% in FY2024; these are assessed only against the regulatory or analytical comparison levels explicitly documented in the workbook.
A10: KEY FINANCIAL SNAPSHOT
A11: METRIC | B11: FY 2022 Restated | C11: FY 2023 | D11: FY 2024 | E11: 3Y / FY2024 VIEW | F11: ANALYST INTERPRETATION
A12: Net Banking Income (€M) | B12: ='📄 INCOME_STATEMENT'!B15 -> 45430 | C12: ='📄 INCOME_STATEMENT'!C15 -> 45874 | D12: ='📄 INCOME_STATEMENT'!D15 -> 48831 | E12: 6.4% FY2024 growth | F12: Revenue momentum strengthened
A13: Net Income — Equity Holders (€M) | B13: ='📄 INCOME_STATEMENT'!B44 -> 9848 | C13: ='📄 INCOME_STATEMENT'!C44 -> 10975 | D13: ='📄 INCOME_STATEMENT'!D44 -> 11688 | E13: =TEXT('📈 RATIOS_PROFITABILITY'!E16,"0.0%")&" Net Income 2-Year CAGR (FY22–FY24)" -> 8.9% Net Income 2-Year CAGR (FY22–FY24) | F13: Earnings growth outpaced revenue
A14: ROE | B14: ='📈 RATIOS_PROFITABILITY'!C8 -> 0.082367652 | C14: ='📈 RATIOS_PROFITABILITY'!D8 -> 0.089599517 | D14: ='📈 RATIOS_PROFITABILITY'!E8 -> 0.092806467 | E14: 9.28% FY2024 | F14: Improving but below stronger EU peers
A15: ROTE | B15: ='📈 RATIOS_PROFITABILITY'!C9 -> 0.089017848 | C15: ='📈 RATIOS_PROFITABILITY'!D9 -> 0.097036304 | D15: ='📈 RATIOS_PROFITABILITY'!E9 -> 0.10065189 | E15: 10.07% FY2024 | F15: Positive trajectory; no external target assessed
A16: Cost-to-Income Ratio | B16: ='📈 RATIOS_EFFICIENCY'!C8 -> 0.65736298 | C16: ='📈 RATIOS_EFFICIENCY'!D8 -> 0.6748049 | D16: ='📈 RATIOS_EFFICIENCY'!E8 -> 0.61831623 | E16: 61.83% FY2024 | F16: Below the 66% analytical comparison
A17: CET1 Ratio | B17: ='📈 RATIOS_CAPITAL'!C8 -> 0.1233 | C17: ='📈 RATIOS_CAPITAL'!D8 -> 0.132 | D17: ='📈 RATIOS_CAPITAL'!E8 -> 0.1287 | E17: Regulatory comparison only | F17: Strong reported capital ratio; no SREP threshold asserted
A18: Liquidity Coverage Ratio (LCR) | B18: ='📈 RATIOS_LIQUIDITY'!C8 -> 1.29 | C18: ='📈 RATIOS_LIQUIDITY'!D8 -> 1.48 | D18: ='📈 RATIOS_LIQUIDITY'!E8 -> 1.37 | E18: 137% FY2024 | F18: Above the 100% regulatory minimum
A19: NPL Ratio | B19: ='📈 RATIOS_ASSET_QUALITY'!C8 -> 0.017 | C19: ='📈 RATIOS_ASSET_QUALITY'!D8 -> 0.017 | D19: ='📈 RATIOS_ASSET_QUALITY'!E8 -> 0.016 | E19: 1.6% FY2024 | F19: Better than the ~2.3% EU reference
A20: Coverage Ratio | B20: ='📈 RATIOS_ASSET_QUALITY'!C9 -> 0.725 | C20: ='📈 RATIOS_ASSET_QUALITY'!D9 -> 0.717 | D20: ='📈 RATIOS_ASSET_QUALITY'!E9 -> 0.697 | E20: 69.7% FY2024 | F20: Adequate but declining
A21: Net Stable Funding Ratio (NSFR) | B21: ='📈 RATIOS_LIQUIDITY'!C9 -> 1.1505 | C21: ='📈 RATIOS_LIQUIDITY'!D9 -> 1.1592 | D21: ='📈 RATIOS_LIQUIDITY'!E9 -> 1.1175 | E21: 111.75% FY2024 | F21: Above the 100% regulatory minimum
A23: 1. EARNINGS PERFORMANCE
A24: Revenue was broadly stable in FY2023 before accelerating in FY2024. NBI increased from €45,430M in restated FY2022 to €48,831M in FY2024. NII declined 9.0% in FY2023 and recovered 2.4% in FY2024, while fees and trading strengthened. Operating expenses fell 2.5% in FY2024. Standard Cost of Risk increased from €2,907M to €2,999M, but other net risk losses declined from €775M to €202M; together these movements supported the 37.4% rise in operating income.
A31: 2. BALANCE SHEET, FUNDING, AND LIQUIDITY
A32: Total assets reached €2,704,908M in FY2024, 4.4% above FY2023. Customer loans were €900,141M and customer deposits €1,034,857M, leaving the loan-to-deposit ratio at 86.98%. This supports a deposit-funded customer lending profile, although the ratio does not capture the Group’s full funding structure. LCR and NSFR remained above the 100% minimum at 137% and 111.75%; HQLA declined to €380,615M.
A38: 3. CASH FLOW ASSESSMENT
A39: The cash-flow statement shows significant operating outflows, including €97,376M in FY2024, largely driven by movements in financial assets and liabilities. The IAS 7 cash-equivalent roll-forward now reconciles exactly in all three years: €317,698M in FY2022, €282,579M in FY2023, and €178,212M in FY2024. These measures include central-bank cash, on-demand balances with credit institutions, and published adjustments, so they are not equivalent to the single balance-sheet line ‘Cash and balances at central banks’.
A46: 4. PROFITABILITY AND EFFICIENCY
A47: ROE improved from 8.24% on the restated FY2022 basis to 9.28%, ROTE from 8.90% to 10.07%, and EPS from €7.52 to €9.57. Net income margin increased from 21.68% to 23.94%. CIR improved to 61.83% in FY2024, below the workbook’s 66% analytical comparison, while NIM declined from 2.07% to 1.77%.
A52: 5. CAPITAL AND CREDIT RISK
A53: Capital remains a core strength. FY2024 CET1 was 12.87%; regulatory reference levels are used for analytical comparison only, and no BNP-specific SREP threshold is asserted. Tier 1, total capital, and leverage ratios also remain above their stated comparison levels. RWA rose to €762,247M in FY2024, explaining why capital ratios moderated from FY2023 despite higher capital balances. Credit quality improved as NPL declined to 1.6%, while coverage fell from 72.5% to 69.7%, leaving less protection if macroeconomic conditions weaken.
A58: 6. KEY RISKS AND FORWARD OUTLOOK
A59: Base case: earnings remain resilient but may grow more slowly if lower policy rates pressure NII. Fee and trading income, cost discipline, and controlled credit costs could partly offset that effect. The key forward-looking sensitivities are continued NIM pressure, Stage 2/3 migration, coverage, RWA growth, and liquidity-buffer trends; these are analytical scenarios rather than sourced BNP forecasts.
... A72: Data were manually extracted from official BNP Paribas annual-results, annual-report, and Pillar 3 documents, standardised in Excel, and cross-checked through the live control register. FY2022 figures affected by IFRS 17/9 use BNP’s restated disclosures for comparability with FY2023–FY2024; reported and restated values are retained separately in IFRS17_RESTATEMENT_NOTE. The analysis excludes forecasts, valuation, consensus estimates, and stress testing.

Sheet 📄 INCOME_STATEMENT
A1: BNP PARIBAS SA — CONSOLIDATED INCOME STATEMENT
A2: FY 2022–FY 2024 | IFRS banking presentation | Net Banking Income format
A3: All figures in €M except percentages, basis points, and per-share data
A4: FY2024 earnings strengthened as NBI grew 6.4% and operating expenses declined 2.5%. Standard Cost of Risk increased 3.2%, while other net risk losses fell 73.9%, lifting operating income 37.4% and net income attributable to equity holders to €11,688M.
A7: LINE ITEM | B7: FY 2022 Restated | C7: FY 2023 | D7: FY 2024 | E7: Δ% 22→23 | F7: Δ% 23→24
A9: NET BANKING INCOME
A10: Net Interest Income | B10: 20933 | C10: 19058 | D10: 19524 | E10: =(C10/B10)-1 -> -0.08957149 | F10: =(D10/C10)-1 -> 0.024451674
A11: Net Fee & Commission Income | B11: 10165 | C11: 9821 | D11: 10701 | E11: =(C11/B11)-1 -> -0.033841613 | F11: =(D11/C11)-1 -> 0.08960391
A12: Net Trading Income | B12: 9352 | C12: 10346 | D12: 11569 | E12: =(C12/B12)-1 -> 0.10628743 | F12: =(D12/C12)-1 -> 0.11820994
A13: Net Income from Other Activities | B13: 2982 | C13: 4235 | D13: 4377 | E13: =(C13/B13)-1 -> 0.42018779 | F13: =(D13/C13)-1 -> 0.033530106
A15: TOTAL NET BANKING INCOME | B15: 45430 | C15: 45874 | D15: 48831 | E15: =(C15/B15)-1 -> 0.0097732776 | F15: =(D15/C15)-1 -> 0.064459171
A17: Identified NBI components subtotal | B17: =SUM(B10:B13) -> 43432 | C17: =SUM(C10:C13) -> 43460 | D17: =SUM(D10:D13) -> 46171
A18: OPERATING EXPENSES
A19: Operating expenses | B19: 27560 | C19: 28713 | D19: 27803 | E19: =(C19/B19)-1 -> 0.041835994 | F19: =(D19/C19)-1 -> -0.031692961
A20: Depreciation & Amortisation | B20: 2304 | C20: 2243 | D20: 2390 | E20: =(C20/B20)-1 -> -0.026475694 | F20: =(D20/C20)-1 -> 0.065537227
A22: TOTAL OPERATING EXPENSES | B22: =B19+B20 -> 29864 | C22: =C19+C20 -> 30956 | D22: =D19+D20 -> 30193 | E22: =(C22/ABS(B22))-1 -> 0.036565765 | F22: =(D22/ABS(C22))-1 -> -0.024647887
A25: GROSS OPERATING INCOME | B25: =B15-B22 -> 15566 | C25: =C15-C22 -> 14918 | D25: =D15-D22 -> 18638 | E25: =(C25/B25)-1 -> -0.041629192 | F25: =(D25/C25)-1 -> 0.24936319
A27: Cost of Risk | B27: 3003 | C27: 2907 | D27: 2999 | E27: =(C27/ABS(B27))-1 -> -0.031968032 | F27: =(D27/ABS(C27))-1 -> 0.031647747
A28: Other net losses for risk on financial instruments | B28: 0 | C28: 775 | D28: 202 | E28: =IFERROR(C28/B28-1,"n/a") -> n/a | F28: =(D28/C28)-1 -> -0.73935484
A29: TOTAL RISK-RELATED CHARGES | B29: =B27+B28 -> 3003 | C29: =C27+C28 -> 3682 | D29: =D27+D28 -> 3201 | E29: =(C29/ABS(B29))-1 -> 0.22610723 | F29: =(D29/ABS(C29))-1 -> -0.13063552
A31: OPERATING INCOME | B31: =B25-B29 -> 12563 | C31: =C25-C29 -> 11236 | D31: =D25-D29 -> 15437 | E31: =(C31/B31)-1 -> -0.10562764 | F31: =(D31/C31)-1 -> 0.3738875
A33: Share of earnings of equity-method entities | B33: 655 | C33: 593 | D33: 701
A34: Net gain on non-current assets | B34: -253 | C34: -104 | D34: -191
A35: Goodwill impact | B35: 249 | C35: 0 | D35: 241
A37: PRE-TAX INCOME | B37: =B31+B33+B34+B35 -> 13214 | C37: =C31+C33+C34+C35 -> 11725 | D37: =D31+D33+D34+D35 -> 16188 | E37: =(C37/B37)-1 -> -0.11268352 | F37: =(D37/C37)-1 -> 0.38063966
A39: CORPORATE INCOME TAX | B39: 3653 | C39: 3266 | D39: 4001
A40: NET INCOME FROM CONTINUING ACTIVITIES | B40: =B37-B39 -> 9561 | C40: =C37-C39 -> 8459 | D40: =D37-D39 -> 12187
A41: Net income from discontinued activities | B41: 687 | C41: 2947 | D41: 0
A42: NET INCOME | B42: =B40+B41 -> 10248 | C42: =C40+C41 -> 11406 | D42: =D40+D41 -> 12187
A43: Net income attributable to minority interests | B43: 400 | C43: 431 | D43: 499
A44: NET INCOME ATTRIBUTABLE TO EQUITY HOLDERS | B44: =B42-B43 -> 9848 | C44: =C42-C43 -> 10975 | D44: =D42-D43 -> 11688 | E44: =(C44/B44)-1 -> 0.11443948 | F44: =(D44/C44)-1 -> 0.064965831
A47: KEY METRICS
A48: Cost-to-Income Ratio (CIR) | B48: =B22/B15 -> 0.65736298 | C48: =C22/C15 -> 0.6748049 | D48: =D22/D15 -> 0.61831623
A49: Cost of Risk (bps) | B49: 31 | C49: 32 | D49: 33
A50: Net Income Margin | B50: =B44/B15 -> 0.21677306 | C50: =C44/C15 -> 0.23924227 | D50: =D44/D15 -> 0.23935615
A51: EPS — Group Share (€) | B51: 7.52 | C51: 8.58 | D51: 9.57

Sheet 🏦 BALANCE_SHEET
A1: BNP PARIBAS SA — CONSOLIDATED BALANCE SHEET
A2: FY 2022–FY 2024 | IFRS banking presentation
A3: All figures in €M | Period end: 31 December
A4: Total assets increased to €2,704,908M in FY2024, supported by customer-loan growth and higher securities balances. Customer deposits grew 4.7%, while total equity reached €134,141M and the balance sheet remained fully reconciled.
A7: ASSETS | B7: 44926 | C7: 45291 | D7: 45657 | E7: Δ% 22→23 | F7: Δ% 23→24
A9: Cash and balances at central banks | B9: 318560 | C9: 288259 | D9: 182496 | E9: =(C9/B9)-1 -> -0.095118659 | F9: =(D9/C9)-1 -> -0.36690268
A10: Financial instruments at fair value through profit or loss
A11: Securities | B11: 166077 | C11: 211634 | D11: 267357 | E11: =(C11/B11)-1 -> 0.27431252 | F11: =(D11/C11)-1 -> 0.2632989
A12: Loans and repurchase agreements | B12: 191125 | C12: 227175 | D12: 225699 | E12: =(C12/B12)-1 -> 0.18862001 | F12: =(D12/C12)-1 -> -0.0064971938
A13: Derivative financial instruments | B13: 327932 | C13: 292079 | D13: 322631 | E13: =(C13/B13)-1 -> -0.10933059 | F13: =(D13/C13)-1 -> 0.10460184
A14: Derivatives used for hedging purposes | B14: 25401 | C14: 21692 | D14: 20851 | E14: =(C14/B14)-1 -> -0.14601787 | F14: =(D14/C14)-1 -> -0.038770053
A15: Financial assets at fair value through equity
A16: Debt securities | B16: 35878 | C16: 50274 | D16: 71430 | E16: =(C16/B16)-1 -> 0.40124868 | F16: =(D16/C16)-1 -> 0.42081394
A17: Equity securities | B17: 2188 | C17: 2275 | D17: 1610 | E17: =(C17/B17)-1 -> 0.03976234 | F17: =(D17/C17)-1 -> -0.29230769
A18: Financial assets at amortised cost
A19: Loans and advances to credit institutions | B19: 32616 | C19: 24335 | D19: 31147 | E19: =(C19/B19)-1 -> -0.25389379 | F19: =(D19/C19)-1 -> 0.27992603
A20: Loans and advances to customers | B20: 857020 | C20: 859200 | D20: 900141 | E20: =(C20/B20)-1 -> 0.0025436979 | F20: =(D20/C20)-1 -> 0.04765014
A21: Debt securities | B21: 114014 | C21: 121161 | D21: 146975 | E21: =(C21/B21)-1 -> 0.062685284 | F21: =(D21/C21)-1 -> 0.21305536
A22: Remeasurement adjustment on interest-rate risk hedged portfolios | B22: -7477 | C22: -2661 | D22: -758 | E22: =(C22/B22)-1 -> -0.6441086 | F22: =(D22/C22)-1 -> -0.71514468
A23: Investments and other assets related to insurance activities | B23: 245475 | C23: 257098 | D23: 286849 | E23: =(C23/B23)-1 -> 0.047349017 | F23: =(D23/C23)-1 -> 0.11571852
A24: Current and deferred tax assets | B24: 5932 | C24: 6556 | D24: 6215 | E24: =(C24/B24)-1 -> 0.10519218 | F24: =(D24/C24)-1 -> -0.052013423
A25: Accrued income and other assets | B25: 208543 | C25: 170758 | D25: 174147 | E25: =(C25/B25)-1 -> -0.18118565 | F25: =(D25/C25)-1 -> 0.019846801
A26: Equity-method investments | B26: 6073 | C26: 6751 | D26: 7862 | E26: =(C26/B26)-1 -> 0.11164169 | F26: =(D26/C26)-1 -> 0.16456821
A27: Property, plant and equipment and investment property | B27: 38468 | C27: 45222 | D27: 50314 | E27: =(C27/B27)-1 -> 0.1755745 | F27: =(D27/C27)-1 -> 0.11260006
A28: Intangible assets | B28: 3790 | C28: 4142 | D28: 4392 | E28: =(C28/B28)-1 -> 0.092875989 | F28: =(D28/C28)-1 -> 0.060357315
A29: Goodwill | B29: 5294 | C29: 5549 | D29: 5550 | E29: =(C29/B29)-1 -> 0.048167737 | F29: =(D29/C29)-1 -> 0.00018021265
A31: TOTAL ASSETS | B31: 2663748 | C31: 2591499 | D31: 2704908 | E31: =(C31/B31)-1 -> -0.027123061 | F31: =(D31/C31)-1 -> 0.043761931
A34: LIABILITIES | B34: 44926 | C34: 45291 | D34: 45657 | E34: Δ% 22→23 | F34: Δ% 23→24
A36: Deposits from central banks | B36: 3054 | C36: 3374 | D36: 3366 | E36: =(C36/B36)-1 -> 0.10478062 | F36: =(D36/C36)-1 -> -0.0023710729
A37: Financial instruments at fair value through profit or loss
A38: Securities | B38: 99155 | C38: 104910 | D38: 79958 | E38: =(C38/B38)-1 -> 0.058040442 | F38: =(D38/C38)-1 -> -0.23784196
A39: Deposits and repurchase agreements | B39: 234076 | C39: 273614 | D39: 304817 | E39: =(C39/B39)-1 -> 0.16891095 | F39: =(D39/C39)-1 -> 0.11404022
A40: Issued debt securities and subordinated debt | B40: 65578 | C40: 83763 | D40: 104934 | E40: =(C40/B40)-1 -> 0.27730336 | F40: =(D40/C40)-1 -> 0.25274883
A41: Derivative financial instruments | B41: 300121 | C41: 278892 | D41: 301953 | E41: =(C41/B41)-1 -> -0.070734804 | F41: =(D41/C41)-1 -> 0.082687922
A42: Derivatives used for hedging purposes | B42: 40001 | C42: 38011 | D42: 36864 | E42: =(C42/B42)-1 -> -0.049748756 | F42: =(D42/C42)-1 -> -0.030175476
A43: Financial liabilities at amortised cost
A44: Deposits from credit institutions | B44: 124718 | C44: 95175 | D44: 66872 | E44: =(C44/B44)-1 -> -0.2368784 | F44: =(D44/C44)-1 -> -0.29737851
A45: Deposits from customers | B45: 1008056 | C45: 988549 | D45: 1034857 | E45: =(C45/B45)-1 -> -0.019351107 | F45: =(D45/C45)-1 -> 0.046844415
A46: Debt securities | B46: 155359 | C46: 191482 | D46: 198119 | E46: =(C46/B46)-1 -> 0.23251308 | F46: =(D46/C46)-1 -> 0.034661221
A47: Subordinated debt | B47: 24160 | C47: 24743 | D47: 31799 | E47: =(C47/B47)-1 -> 0.024130795 | F47: =(D47/C47)-1 -> 0.28517156
A48: Remeasurement adjustment on interest‑rate risk hedged portfolios | B48: -20201 | C48: -14175 | D48: -10696 | E48: =(C48/B48)-1 -> -0.29830206 | F48: =(D48/C48)-1 -> -0.2454321
A49: Current and deferred tax liabilities | B49: 2979 | C49: 3821 | D49: 3657 | E49: =(C49/B49)-1 -> 0.28264518 | F49: =(D49/C49)-1 -> -0.042920701
A50: Accrued expenses and other liabilities | B50: 185010 | C50: 143673 | D50: 136955 | E50: =(C50/B50)-1 -> -0.22343117 | F50: =(D50/C50)-1 -> -0.04675896
A51: Liabilities related to insurance contracts | B51: 209772 | C51: 218043 | D51: 247699 | E51: =(C51/B51)-1 -> 0.039428522 | F51: =(D51/C51)-1 -> 0.13600987
A52: Financial liabilities related to insurance activities | B52: 18858 | C52: 18239 | D52: 19807 | E52: =(C52/B52)-1 -> -0.032824266 | F52: =(D52/C52)-1 -> 0.085969626
A53: Provisions for contingencies and charges | B53: 10040 | C53: 10518 | D53: 9806 | E53: =(C53/B53)-1 -> 0.047609562 | F53: =(D53/C53)-1 -> -0.067693478
A55: TOTAL LIABILITIES | B55: 2537738 | C55: 2462632 | D55: 2570767 | E55: =(C55/B55)-1 -> -0.029595648 | F55: =(D55/C55)-1 -> 0.043910337
A57: EQUITY | B57: 44926 | C57: 45291 | D57: 45657 | E57: Δ% 22→23 | F57: Δ% 23→24
A59: Share capital, additional paid‑in capital and retained earnings | B59: 115149 | C59: 115809 | D59: 118957 | E59: =IFERROR(C59/B59-1,"") -> 0.0057317041 | F59: =IFERROR(D59/C59-1,"") -> 0.027182689
A60: Net income attributable to shareholders (FY2022 reported basis for balance-sheet reconciliation) | B60: 10196 | C60: 10975 | D60: 11688 | E60: =IFERROR(C60/B60-1,"") -> 0.076402511 | F60: =IFERROR(D60/C60-1,"") -> 0.064965831
A61: Total capital, retained earnings and net income | B61: 125345 | C61: 126784 | D61: 130645 | E61: =IFERROR(C61/B61-1,"") -> 0.011480314 | F61: =IFERROR(D61/C61-1,"") -> 0.03045337
A62: Changes in assets and liabilities recognised directly in equity | B62: -3553 | C62: -3042 | D62: -2508 | E62: =IFERROR(C62/B62-1,"") -> -0.14382212 | F62: =IFERROR(D62/C62-1,"") -> -0.17554241
A63: Shareholders’ equity | B63: 121792 | C63: 123742 | D63: 128137 | E63: =IFERROR(C63/B63-1,"") -> 0.016010904 | F63: =IFERROR(D63/C63-1,"") -> 0.035517448
A64: Minority interests | B64: 4763 | C64: 5125 | D64: 6004 | E64: =IFERROR(C64/B64-1,"") -> 0.076002519 | F64: =IFERROR(D64/C64-1,"") -> 0.1715122
A66: TOTAL EQUITY | B66: 126555 | C66: 128867 | D66: 134141 | E66: =IFERROR(C66/B66-1,"") -> 0.018268737 | F66: =IFERROR(D66/C66-1,"") -> 0.040925916
A67: TOTAL LIABILITIES + EQUITY | B67: 2663748 | C67: 2591499 | D67: 2704908 | E67: =IFERROR(C67/B67-1,"") -> -0.027123061 | F67: =IFERROR(D67/C67-1,"") -> 0.043761931
A68: BALANCE CHECK — Assets less Liabilities & Equity | B68: =B31-B67 -> 0 | C68: =C31-C67 -> 0 | D68: =D31-D67 -> 0

Sheet 💰 CASH_FLOW
A1: BNP PARIBAS SA — CONSOLIDATED CASH FLOW STATEMENT
A2: FY 2022–FY 2024 | IFRS (IAS 7) | Indirect method
A3: All figures in €M except percentages
A4: FY2024 cash generation was affected by a €97,376M operating outflow, mainly from movements in financial assets and liabilities. Investing cash flow was near neutral, while financing activities produced a €6,418M outflow.
A7: CASH-FLOW ITEM | B7: FY 2022 | C7: FY 2023 | D7: FY 2024 | E7: Δ% 22→23 | F7: Δ% 23→24
A9: A. OPERATING ACTIVITIES
A10: Pre-tax income from continuing activities | B10: 13214 | C10: 11725 | D10: 16188 | E10: =(C10/B10)-1 -> -0.11268352 | F10: =(D10/C10)-1 -> 0.38063966
A11: Pre-tax income from discontinued activities | B11: 823 | C11: 3658 | D11: 0 | E11: =(C11/B11)-1 -> 3.4447145 | F11: =(D11/C11)-1 -> -1
A12: Non-monetary items included in pre-tax net income and other adjustments | B12: 21838 | C12: 8495 | D12: 11094 | E12: =(C12/B12)-1 -> -0.61099918 | F12: =(D12/C12)-1 -> 0.30594467
A13: Net depreciation/amortisation expense | B13: 6465 | C13: 6245 | D13: 7272 | E13: =(C13/B13)-1 -> -0.034029389 | F13: =(D13/C13)-1 -> 0.16445156
A14: Impairment of goodwill and other non-current assets | B14: 91 | C14: -32 | D14: 21 | E14: =(C14/B14)-1 -> -1.3516484 | F14: =(D14/C14)-1 -> -1.65625
A15: Net addition to provisions | B15: 3193 | C15: 3646 | D15: 3023 | E15: =(C15/B15)-1 -> 0.14187285 | F15: =(D15/C15)-1 -> -0.17087219
A16: Variation of assets/liabilities related to insurance contracts | B16: -837 | C16: -6240 | D16: 3181 | E16: =(C16/B16)-1 -> 6.4551971 | F16: =(D16/C16)-1 -> -1.5097756
A17: Share of earnings of equity-method entities | B17: -655 | C17: -593 | D17: -701 | E17: =(C17/B17)-1 -> -0.094656489 | F17: =(D17/C17)-1 -> 0.18212479
A18: Net income from investing activities | B18: 265 | C18: -3600 | D18: -277 | E18: =(C18/B18)-1 -> -14.584906 | F18: =(D18/C18)-1 -> -0.92305556
A19: Net income (expense) from financing activities | B19: -1192 | C19: 506 | D19: -604 | E19: =(C19/B19)-1 -> -1.4244966 | F19: =(D19/C19)-1 -> -2.1936759
A20: Other movements | B20: 14508 | C20: 8563 | D20: -821 | E20: =(C20/B20)-1 -> -0.40977392 | F20: =(D20/C20)-1 -> -1.0958776
A21: Net decrease related to assets and liabilities | B21: -88712 | C21: -58119 | D21: -124658 | E21: =(C21/B21)-1 -> -0.34485752 | F21: =(D21/C21)-1 -> 1.1448752
... A27: NET CASH FROM OPERATING ACTIVITIES | B27: -52837 | C27: -34241 | D27: -97376 | E27: =(C27/B27)-1 -> -0.35195034 | F27: =(D27/C27)-1 -> 1.8438422
A29: B. INVESTING ACTIVITIES
A30: Net increase related to acquisitions and disposals of consolidated entities | B30: 366 | C30: 9520 | D30: 1956 | E30: =(C30/B30)-1 -> 25.010929 | F30: =(D30/C30)-1 -> -0.79453782
A31: Net decrease related to property, plant and equipment and intangible assets | B31: -2529 | C31: -2216 | D31: -2136 | E31: =(C31/B31)-1 -> -0.12376433 | F31: =(D31/C31)-1 -> -0.036101083
A33: NET CASH FROM INVESTING ACTIVITIES | B33: =B30+B31 -> -2163 | C33: =C30+C31 -> 7304 | D33: =D30+D31 -> -180 | E33: =(C33/B33)-1 -> -4.3767915 | F33: =(D33/C33)-1 -> -1.024644
A35: C. FINANCING ACTIVITIES
A36: Decrease in cash and cash equivalents related to transactions with shareholders | B36: -2578 | C36: -8698 | D36: -8756 | E36: =(C36/B36)-1 -> 2.3739333 | F36: =(D36/C36)-1 -> 0.0066681996
A37: Increase in cash and cash equivalents generated by other financing activities | B37: 11828 | C37: 4022 | D37: 2338 | E37: =(C37/B37)-1 -> -0.65995942 | F37: =(D37/C37)-1 -> -0.41869717
A39: NET CASH FROM FINANCING ACTIVITIES | B39: =B36+B37 -> 9250 | C39: =C36+C37 -> -4676 | D39: =D36+D37 -> -6418 | E39: =(C39/B39)-1 -> -1.5055135 | F39: =(D39/C39)-1 -> 0.37254063
A40: EFFECT OF MOVEMENT IN EXCHANGE RATES | B40: 1030 | C40: -3506 | D40: -393 | E40: =(C40/B40)-1 -> -4.4038835 | F40: =(D40/C40)-1 -> -0.88790645
A41: NET DECREASE IN CASH AND CASH EQUIVALENTS | B41: -44720 | C41: -35119 | D41: -104367 | E41: =(C41/B41)-1 -> -0.21469141 | F41: =(D41/C41)-1 -> 1.9718101
A44: CASH AND CASH EQUIVALENTS RECONCILIATION | B44: FY 2022 | C44: FY 2023 | D44: FY 2024 | E44: Δ% 22→23 | F44: Δ% 23→24
A45: Opening cash and cash equivalents | B45: 362418 | C45: 317698 | D45: 282579 | E45: =IFERROR(C45/B45-1,"") -> -0.12339343 | F45: =IFERROR(D45/C45-1,"") -> -0.11054209
A46: Net decrease in cash and cash equivalents | B46: =B41 -> -44720 | C46: =C41 -> -35119 | D46: =D41 -> -104367 | E46: =IFERROR(C46/B46-1,"") -> -0.21469141 | F46: =IFERROR(D46/C46-1,"") -> 1.9718101
A47: Calculated closing cash and cash equivalents | B47: =B45+B46 -> 317698 | C47: =C45+C46 -> 282579 | D47: =D45+D46 -> 178212 | E47: =IFERROR(C47/B47-1,"") -> -0.11054209 | F47: =IFERROR(D47/C47-1,"") -> -0.36933742
A48: Reported closing cash and cash equivalents | B48: 317698 | C48: 282579 | D48: 178212 | E48: =IFERROR(C48/B48-1,"") -> -0.11054209 | F48: =IFERROR(D48/C48-1,"") -> -0.36933742
A49: ROLL-FORWARD RECONCILIATION CHECK | B49: =B47-B48 -> 0 | C49: =C47-C48 -> 0 | D49: =D47-D48 -> 0 | E49: €0M expected | F49: PASS when all years = €0M
A51: CLOSING CASH-EQUIVALENT COMPOSITION | B51: FY 2022 | C51: FY 2023 | D51: FY 2024 | E51: STATUS | F51: SOURCE BASIS
A52: Cash and amounts due from central banks | B52: 318581 | C52: 288279 | D52: 182511 | E52: Published component | F52: BNP consolidated cash-flow statement
A53: Due to central banks | B53: -3054 | C53: -3374 | D53: -3366 | E53: Published component | F53: BNP consolidated cash-flow statement
A54: On-demand deposits with credit institutions | B54: 11927 | C54: 8352 | D54: 9482 | E54: Published component | F54: BNP consolidated cash-flow statement
A55: On-demand loans from credit institutions | B55: -12538 | C55: -10770 | D55: -10608 | E55: Published component | F55: BNP consolidated cash-flow statement
A56: Accrued-interest deduction / assets held for sale | B56: 2782 | C56: 92 | D56: 193 | E56: Published adjustment | F56: BNP consolidated cash-flow statement
A57: COMPOSITION RECONCILIATION CHECK | B57: =SUM(B52:B56)-B48 -> 0 | C57: =SUM(C52:C56)-C48 -> 0 | D57: =SUM(D52:D56)-D48 -> 0 | E57: PASS | F57: All components reconcile to the reported IAS 7 closing balance
A59: METRIC | B59: FY 2022 Restated | C59: FY 2023 | D59: FY 2024 | E59: Δ% 22→23 | F59: Δ% 23→24
A60: Total Capital Returned (€M) — proxy from CF line transactions with shareholders | B60: 2578 | C60: 8698 | D60: 8756 | E60: =IFERROR(C60/B60-1,"") -> 2.3739333 | F60: =IFERROR(D60/C60-1,"") -> 0.0066681996
A61: Capital Return / Net Income (%) | B61: =B60/'📄 INCOME_STATEMENT'!B44 -> 0.26177904 | C61: =C60/'📄 INCOME_STATEMENT'!C44 -> 0.79252847 | D61: =D60/'📄 INCOME_STATEMENT'!D44 -> 0.74914442 | E61: =C61-B61 -> 0.53074943 | F61: =D61-C61 -> -0.043384052

Sheet 🧮VARIANCE BRIDGE
A1: BNP PARIBAS — NET INCOME VARIANCE BRIDGE
A2: FY 2022 → FY 2023 → FY 2024 | ECB-style earnings attribution
A3: All values in €M | Drivers linked directly to the consolidated income statement
A4: Net income increased by €1,127M in FY2023 and €713M in FY2024. FY2023 standard Cost of Risk improved by €96M but other net risk losses added a €775M charge; FY2024 standard Cost of Risk increased by €92M while other net risk losses improved by €573M.
A6: FY 2022 → FY 2023 BRIDGE
A7: DRIVER | B7: CHANGE (€M) | C7: RUNNING BALANCE | D7: DIRECTION | E7: SOURCE / STATUS
A8: Opening net income FY2022 (restated) | B8: ='📄 INCOME_STATEMENT'!B44 -> 9848 | C8: =B8 -> 9848 | D8: Restated | E8: Income statement
A9: Net Interest Income | B9: ='📄 INCOME_STATEMENT'!C10-'📄 INCOME_STATEMENT'!B10 -> -1875 | C9: =C8+B9 -> 7973 | D9: =IF(B9>0,"Positive",IF(B9<0,"Negative","Neutral")) -> Negative | E9: NII movement
A10: Fee & Commission Income | B10: ='📄 INCOME_STATEMENT'!C11-'📄 INCOME_STATEMENT'!B11 -> -344 | C10: =C9+B10 -> 7629 | D10: =IF(B10>0,"Positive",IF(B10<0,"Negative","Neutral")) -> Negative | E10: Fees movement
A11: Trading Income | B11: ='📄 INCOME_STATEMENT'!C12-'📄 INCOME_STATEMENT'!B12 -> 994 | C11: =C10+B11 -> 8623 | D11: =IF(B11>0,"Positive",IF(B11<0,"Negative","Neutral")) -> Positive | E11: Trading movement
A12: Other operating activities | B12: ='📄 INCOME_STATEMENT'!C13-'📄 INCOME_STATEMENT'!B13 -> 1253 | C12: =C11+B12 -> 9876 | D12: =IF(B12>0,"Positive",IF(B12<0,"Negative","Neutral")) -> Positive | E12: Other activities movement
A13: Unallocated NBI components | B13: =('📄 INCOME_STATEMENT'!C15-SUM('📄 INCOME_STATEMENT'!C10:C13))-('📄 INCOME_STATEMENT'!B15-SUM('📄 INCOME_STATEMENT'!B10:B13)) -> 416 | C13: =C12+B13 -> 10292 | D13: =IF(B13>0,"Positive",IF(B13<0,"Negative","Neutral")) -> Positive | E13: NBI reconciliation
A14: Operating expenses effect | B14: =-('📄 INCOME_STATEMENT'!C22-'📄 INCOME_STATEMENT'!B22) -> -1092 | C14: =C13+B14 -> 9200 | D14: =IF(B14>0,"Positive",IF(B14<0,"Negative","Neutral")) -> Negative | E14: Lower expenses = positive
A15: Cost of Risk effect | B15: =-('📄 INCOME_STATEMENT'!C27-'📄 INCOME_STATEMENT'!B27) -> 96 | C15: =C14+B15 -> 9296 | D15: =IF(B15>0,"Positive",IF(B15<0,"Negative","Neutral")) -> Positive | E15: Lower Cost of Risk = positive
A16: Other net losses for risk on financial instruments effect | B16: =-('📄 INCOME_STATEMENT'!C28-'📄 INCOME_STATEMENT'!B28) -> -775 | C16: =C15+B16 -> 8521 | D16: =IF(B16>0,"Positive",IF(B16<0,"Negative","Neutral")) -> Negative | E16: Lower other net risk losses = positive
A17: Non-operating items | B17: =('📄 INCOME_STATEMENT'!C33+'📄 INCOME_STATEMENT'!C34+'📄 INCOME_STATEMENT'!C35)-('📄 INCOME_STATEMENT'!B33+'📄 INCOME_STATEMENT'!B34+'📄 INCOME_STATEMENT'!B35) -> -162 | C17: =C16+B17 -> 8359 | D17: =IF(B17>0,"Positive",IF(B17<0,"Negative","Neutral")) -> Negative | E17: Equity earnings / gains / goodwill
A18: Tax effect | B18: =-('📄 INCOME_STATEMENT'!C39-'📄 INCOME_STATEMENT'!B39) -> 387 | C18: =C17+B18 -> 8746 | D18: =IF(B18>0,"Positive",IF(B18<0,"Negative","Neutral")) -> Positive | E18: Lower tax = positive
A19: Discontinued operations & minority interests | B19: =('📄 INCOME_STATEMENT'!C44-'📄 INCOME_STATEMENT'!B44)-SUM(B9:B18) -> 2229 | C19: =C18+B19 -> 10975 | D19: =IF(B19>0,"Positive",IF(B19<0,"Negative","Neutral")) -> Positive | E19: Reconciliation item
A20: Closing net income FY2023 | B20: ='📄 INCOME_STATEMENT'!C44 -> 10975 | C20: =B20 -> 10975 | D20: Reported | E20: Income statement
A21: RECONCILIATION CHECK | B21: =C19-B20 -> 0 | C21: =IF(B21=0,"PASS","CHECK") -> PASS
A23: FY 2023 → FY 2024 BRIDGE
A24: DRIVER | B24: CHANGE (€M) | C24: RUNNING BALANCE | D24: DIRECTION | E24: SOURCE / STATUS
A25: Opening net income FY2023 | B25: ='📄 INCOME_STATEMENT'!C44 -> 10975 | C25: =B25 -> 10975 | D25: Reported | E25: Income statement
A26: Net Interest Income | B26: ='📄 INCOME_STATEMENT'!D10-'📄 INCOME_STATEMENT'!C10 -> 466 | C26: =C25+B26 -> 11441 | D26: =IF(B26>0,"Positive",IF(B26<0,"Negative","Neutral")) -> Positive | E26: NII movement
A27: Fee & Commission Income | B27: ='📄 INCOME_STATEMENT'!D11-'📄 INCOME_STATEMENT'!C11 -> 880 | C27: =C26+B27 -> 12321 | D27: =IF(B27>0,"Positive",IF(B27<0,"Negative","Neutral")) -> Positive | E27: Fees movement
A28: Trading Income | B28: ='📄 INCOME_STATEMENT'!D12-'📄 INCOME_STATEMENT'!C12 -> 1223 | C28: =C27+B28 -> 13544 | D28: =IF(B28>0,"Positive",IF(B28<0,"Negative","Neutral")) -> Positive | E28: Trading movement
A29: Other operating activities | B29: ='📄 INCOME_STATEMENT'!D13-'📄 INCOME_STATEMENT'!C13 -> 142 | C29: =C28+B29 -> 13686 | D29: =IF(B29>0,"Positive",IF(B29<0,"Negative","Neutral")) -> Positive | E29: Other activities movement
A30: Unallocated NBI components | B30: =('📄 INCOME_STATEMENT'!D15-SUM('📄 INCOME_STATEMENT'!D10:D13))-('📄 INCOME_STATEMENT'!C15-SUM('📄 INCOME_STATEMENT'!C10:C13)) -> 246 | C30: =C29+B30 -> 13932 | D30: =IF(B30>0,"Positive",IF(B30<0,"Negative","Neutral")) -> Positive | E30: NBI reconciliation
A31: Operating expenses effect | B31: =-('📄 INCOME_STATEMENT'!D22-'📄 INCOME_STATEMENT'!C22) -> 763 | C31: =C30+B31 -> 14695 | D31: =IF(B31>0,"Positive",IF(B31<0,"Negative","Neutral")) -> Positive | E31: Lower expenses = positive
A32: Cost of Risk effect | B32: =-('📄 INCOME_STATEMENT'!D27-'📄 INCOME_STATEMENT'!C27) -> -92 | C32: =C31+B32 -> 14603 | D32: =IF(B32>0,"Positive",IF(B32<0,"Negative","Neutral")) -> Negative | E32: Lower Cost of Risk = positive
A33: Other net losses for risk on financial instruments effect | B33: =-('📄 INCOME_STATEMENT'!D28-'📄 INCOME_STATEMENT'!C28) -> 573 | C33: =C32+B33 -> 15176 | D33: =IF(B33>0,"Positive",IF(B33<0,"Negative","Neutral")) -> Positive | E33: Lower other net risk losses = positive
A34: Non-operating items | B34: =('📄 INCOME_STATEMENT'!D33+'📄 INCOME_STATEMENT'!D34+'📄 INCOME_STATEMENT'!D35)-('📄 INCOME_STATEMENT'!C33+'📄 INCOME_STATEMENT'!C34+'📄 INCOME_STATEMENT'!C35) -> 262 | C34: =C33+B34 -> 15438 | D34: =IF(B34>0,"Positive",IF(B34<0,"Negative","Neutral")) -> Positive | E34: Equity earnings / gains / goodwill
A35: Tax effect | B35: =-('📄 INCOME_STATEMENT'!D39-'📄 INCOME_STATEMENT'!C39) -> -735 | C35: =C34+B35 -> 14703 | D35: =IF(B35>0,"Positive",IF(B35<0,"Negative","Neutral")) -> Negative | E35: Lower tax = positive
A36: Discontinued operations & minority interests | B36: =('📄 INCOME_STATEMENT'!D44-'📄 INCOME_STATEMENT'!C44)-SUM(B26:B35) -> -3015 | C36: =C35+B36 -> 11688 | D36: =IF(B36>0,"Positive",IF(B36<0,"Negative","Neutral")) -> Negative | E36: Reconciliation item
A37: Closing net income FY2024 | B37: ='📄 INCOME_STATEMENT'!D44 -> 11688 | C37: =B37 -> 11688 | D37: Reported | E37: Income statement
A38: RECONCILIATION CHECK | B38: =C36-B37 -> 0 | C38: =IF(B38=0,"PASS","CHECK") -> PASS
A40: P&L LINE VARIANCE SUMMARY
A41: ITEM | B41: FY 2022 | C41: FY 2023 | D41: Δ€M 22→23 | E41: Δ% 22→23 | F41: FY 2023 | G41: FY 2024 | H41: Δ€M 23→24 | I41: Δ% 23→24
A42: Total NBI | B42: ='📄 INCOME_STATEMENT'!B15 -> 45430 | C42: ='📄 INCOME_STATEMENT'!C15 -> 45874 | D42: =C42-B42 -> 444 | E42: =IFERROR(C42/B42-1,"") -> 0.0097732776 | F42: ='📄 INCOME_STATEMENT'!C15 -> 45874 | G42: ='📄 INCOME_STATEMENT'!D15 -> 48831 | H42: =G42-F42 -> 2957 | I42: =IFERROR(G42/F42-1,"") -> 0.064459171
A43: Net Interest Income | B43: ='📄 INCOME_STATEMENT'!B10 -> 20933 | C43: ='📄 INCOME_STATEMENT'!C10 -> 19058 | D43: =C43-B43 -> -1875 | E43: =IFERROR(C43/B43-1,"") -> -0.08957149 | F43: ='📄 INCOME_STATEMENT'!C10 -> 19058 | G43: ='📄 INCOME_STATEMENT'!D10 -> 19524 | H43: =G43-F43 -> 466 | I43: =IFERROR(G43/F43-1,"") -> 0.024451674
A44: Fee & Commission Income | B44: ='📄 INCOME_STATEMENT'!B11 -> 10165 | C44: ='📄 INCOME_STATEMENT'!C11 -> 9821 | D44: =C44-B44 -> -344 | E44: =IFERROR(C44/B44-1,"") -> -0.033841613 | F44: ='📄 INCOME_STATEMENT'!C11 -> 9821 | G44: ='📄 INCOME_STATEMENT'!D11 -> 10701 | H44: =G44-F44 -> 880 | I44: =IFERROR(G44/F44-1,"") -> 0.08960391
A45: Trading Income | B45: ='📄 INCOME_STATEMENT'!B12 -> 9352 | C45: ='📄 INCOME_STATEMENT'!C12 -> 10346 | D45: =C45-B45 -> 994 | E45: =IFERROR(C45/B45-1,"") -> 0.10628743 | F45: ='📄 INCOME_STATEMENT'!C12 -> 10346 | G45: ='📄 INCOME_STATEMENT'!D12 -> 11569 | H45: =G45-F45 -> 1223 | I45: =IFERROR(G45/F45-1,"") -> 0.11820994
A46: Total Operating Expenses | B46: ='📄 INCOME_STATEMENT'!B22 -> 29864 | C46: ='📄 INCOME_STATEMENT'!C22 -> 30956 | D46: =C46-B46 -> 1092 | E46: =IFERROR(C46/B46-1,"") -> 0.036565765 | F46: ='📄 INCOME_STATEMENT'!C22 -> 30956 | G46: ='📄 INCOME_STATEMENT'!D22 -> 30193 | H46: =G46-F46 -> -763 | I46: =IFERROR(G46/F46-1,"") -> -0.024647887
A47: Gross Operating Income | B47: ='📄 INCOME_STATEMENT'!B25 -> 15566 | C47: ='📄 INCOME_STATEMENT'!C25 -> 14918 | D47: =C47-B47 -> -648 | E47: =IFERROR(C47/B47-1,"") -> -0.041629192 | F47: ='📄 INCOME_STATEMENT'!C25 -> 14918 | G47: ='📄 INCOME_STATEMENT'!D25 -> 18638 | H47: =G47-F47 -> 3720 | I47: =IFERROR(G47/F47-1,"") -> 0.24936319
A48: Cost of Risk | B48: ='📄 INCOME_STATEMENT'!B27 -> 3003 | C48: ='📄 INCOME_STATEMENT'!C27 -> 2907 | D48: =C48-B48 -> -96 | E48: =IFERROR(C48/B48-1,"") -> -0.031968032 | F48: ='📄 INCOME_STATEMENT'!C27 -> 2907 | G48: ='📄 INCOME_STATEMENT'!D27 -> 2999 | H48: =G48-F48 -> 92 | I48: =IFERROR(G48/F48-1,"") -> 0.031647747
A49: Net Income — Group Share | B49: ='📄 INCOME_STATEMENT'!B44 -> 9848 | C49: ='📄 INCOME_STATEMENT'!C44 -> 10975 | D49: =C49-B49 -> 1127 | E49: =IFERROR(C49/B49-1,"") -> 0.11443948 | F49: ='📄 INCOME_STATEMENT'!C44 -> 10975 | G49: ='📄 INCOME_STATEMENT'!D44 -> 11688 | H49: =G49-F49 -> 713 | I49: =IFERROR(G49/F49-1,"") -> 0.064965831
A52: MANAGEMENT TAKEAWAY
A53: FY2023 earnings growth depended on trading and reconciliation items because NII, fees, operating costs, and total risk-related charges were adverse, although standard Cost of Risk improved by €96M. FY2024 delivery was broader: revenue and operating expenses improved; standard Cost of Risk increased by €92M, while other net risk losses fell by €573M.

Sheet 📈 RATIOS_PROFITABILITY
A1: BNP PARIBAS — PROFITABILITY RATIOS
A2: FY 2022–FY 2024 | ECB/EBA-aligned definitions
A3: Rate metrics in % | EPS in € per share | Values linked to the financial statements where available
A4: Profitability improved across the period: ROE reached 9.28%, ROTE exceeded 10%, and net income margin rose from 21.68% to 23.94%. The key watchpoint is NIM compression from 2.07% to 1.77%, although NII returned to growth in FY2024.
A6: PROFITABILITY SCORECARD
A7: RATIO | B7: FORMULA / DEFINITION | C7: FY 2022 Restated | D7: FY 2023 | E7: FY 2024 | F7: TREND | G7: BENCHMARK / SIGNAL
A8: Return on Equity (ROE) | B8: Net income — group share / average total equity | C8: ='📄 INCOME_STATEMENT'!B44/ANALYTICAL_INPUTS!C7 -> 0.082367652 | D8: ='📄 INCOME_STATEMENT'!C44/ANALYTICAL_INPUTS!C8 -> 0.089599517 | E8: ='📄 INCOME_STATEMENT'!D44/ANALYTICAL_INPUTS!C9 -> 0.092806467 | F8: ↗ | G8: ECB Q2 2024 aggregate: 10.11%
A9: Return on Tangible Equity (ROTE) | B9: Net income — group share / average tangible equity | C9: ='📄 INCOME_STATEMENT'!B44/ANALYTICAL_INPUTS!C10 -> 0.089017848 | D9: ='📄 INCOME_STATEMENT'!C44/ANALYTICAL_INPUTS!C11 -> 0.097036304 | E9: ='📄 INCOME_STATEMENT'!D44/ANALYTICAL_INPUTS!C12 -> 0.10065189 | F9: ↗ | G9: Improving; no external benchmark assessed
A10: Return on Assets (ROA) | B10: Net income — group share / average total assets | C10: ='📄 INCOME_STATEMENT'!B44/ANALYTICAL_INPUTS!C13 -> 0.0037174946 | D10: ='📄 INCOME_STATEMENT'!C44/ANALYTICAL_INPUTS!C14 -> 0.004176778 | E10: ='📄 INCOME_STATEMENT'!D44/ANALYTICAL_INPUTS!C15 -> 0.0044135581 | F10: ↗ | G10: ECB range varies; see BENCHMARKS
A11: Net Interest Margin (NIM) | B11: Net interest income / average earning assets | C11: ='📄 INCOME_STATEMENT'!B10/ANALYTICAL_INPUTS!C16 -> 0.020698128 | D11: ='📄 INCOME_STATEMENT'!C10/ANALYTICAL_INPUTS!C17 -> 0.018198155 | E11: ='📄 INCOME_STATEMENT'!D10/ANALYTICAL_INPUTS!C18 -> 0.01771155 | F11: ↘ | G11: ECB Q2 2024 aggregate: 1.61%
A12: NII Growth | B12: Current-year NII / prior-year NII − 1 | C12: n/a | D12: ='📄 INCOME_STATEMENT'!C10/'📄 INCOME_STATEMENT'!B10-1 -> -0.08957149 | E12: ='📄 INCOME_STATEMENT'!D10/'📄 INCOME_STATEMENT'!C10-1 -> 0.024451674 | F12: ↘↗ | G12: Rate-cycle sensitivity
A13: NBI Growth | B13: Current-year NBI / prior-year NBI − 1 | C13: n/a | D13: ='📄 INCOME_STATEMENT'!C15/'📄 INCOME_STATEMENT'!B15-1 -> 0.0097732776 | E13: ='📄 INCOME_STATEMENT'!D15/'📄 INCOME_STATEMENT'!C15-1 -> 0.064459171 | F13: ↗ | G13: Revenue momentum
A14: Net Income Margin | B14: Net income — group share / total NBI | C14: ='📄 INCOME_STATEMENT'!B44/'📄 INCOME_STATEMENT'!B15 -> 0.21677306 | D14: ='📄 INCOME_STATEMENT'!C44/'📄 INCOME_STATEMENT'!C15 -> 0.23924227 | E14: ='📄 INCOME_STATEMENT'!D44/'📄 INCOME_STATEMENT'!D15 -> 0.23935615 | F14: ↗ | G14: Higher is better
A15: Earnings per Share (€) | B15: Net income — group share / weighted-average shares | C15: ='📄 INCOME_STATEMENT'!B51 -> 7.52 | D15: ='📄 INCOME_STATEMENT'!C51 -> 8.58 | E15: ='📄 INCOME_STATEMENT'!D51 -> 9.57 | F15: ↗ | G15: Strong EPS growth
A16: Net Income 2-Year CAGR (FY22–FY24) | B16: (Net income FY2024 / FY2022)^(1/2) − 1 | C16: n/a | D16: n/a | E16: =('📄 INCOME_STATEMENT'!D44/'📄 INCOME_STATEMENT'!B44)^(1/2)-1 -> 0.08942185 | F16: ↗ | G16: Strong delivery
A19: METHODOLOGY NOTES
A20: Tangible equity equals shareholders’ equity less goodwill and intangible assets. Earning assets comprise customer and bank loans plus debt securities at amortised cost and FVOCI. Average-balance denominators and their annual-report source sections are documented in ANALYTICAL_INPUTS.
A22: MANAGEMENT TAKEAWAY
A23: The earnings profile strengthened through FY2024, with rising returns, margins, and EPS. On the consistent restated basis, net income grew at an 8.94% two-year CAGR. Continued NIM compression means future growth must increasingly rely on fees, trading, cost discipline, and balance-sheet efficiency.

Sheet 📈 RATIOS_LIQUIDITY
A1: BNP PARIBAS — LIQUIDITY RATIOS
A2: FY 2022–FY 2024 | CRR Article 412 | LCR Delegated Act | NSFR CRR2
A3: Source: BNP Paribas Pillar 3 annual disclosures | HQLA values in €M
A4: Liquidity ratios remained above the 100% regulatory minimum throughout the period. FY2024 LCR closed at 137% and NSFR at 111.75%, while customer deposits exceeded customer loans; HQLA declined to €380,615M.
A6: LIQUIDITY SCORECARD
A7: RATIO | B7: REGULATORY DEFINITION | C7: FY 2022 | D7: FY 2023 | E7: FY 2024 | F7: TREND | G7: MINIMUM / TARGET | H7: SIGNAL
A8: Liquidity Coverage Ratio (LCR) | B8: HQLA / 30-day stressed net cash outflows | C8: 1.29 | D8: 1.48 | E8: 1.37 | F8: ↗↘ | G8: ≥100% | H8: Compliant
A9: Net Stable Funding Ratio (NSFR) | B9: Available stable funding / required stable funding | C9: 1.1505 | D9: 1.1592 | E9: 1.1175 | F9: → | G9: ≥100% | H9: Compliant
A10: High Quality Liquid Assets (€M) | B10: Reported HQLA stock, predominantly Level 1 assets | C10: 454812 | D10: 408476 | E10: 380615 | F10: ↘ | G10: Liquidity buffer | H10: Strong stock; declining
A11: Loan-to-Deposit Ratio | B11: Gross customer loans / customer deposits | C11: ='🏦 BALANCE_SHEET'!B20/'🏦 BALANCE_SHEET'!B45 -> 0.85017102 | D11: ='🏦 BALANCE_SHEET'!C20/'🏦 BALANCE_SHEET'!C45 -> 0.86915267 | E11: ='🏦 BALANCE_SHEET'!D20/'🏦 BALANCE_SHEET'!D45 -> 0.86982163 | F11: → | G11: <100% ideal | H11: Deposits exceed customer loans
A12: Deposit Growth | B12: Annual change in customer deposits | C12: n/a | D12: ='🏦 BALANCE_SHEET'!C45/'🏦 BALANCE_SHEET'!B45-1 -> -0.019351107 | E12: ='🏦 BALANCE_SHEET'!D45/'🏦 BALANCE_SHEET'!C45-1 -> 0.046844415 | F12: ↘↗ | G12: n/a | H12: Recovered in FY2024
A15: REGULATORY NOTES
A16: LCR and NSFR are assessed against the 100% minimum. A loan-to-deposit ratio below 100% supports a deposit-funded customer lending profile, although it does not capture the full funding structure of the Group.
A20: MANAGEMENT TAKEAWAY
A21: BNP Paribas maintains liquidity ratios above the stated minimum and customer deposits above customer loans. The principal watchpoint is the decline in HQLA from €454,812M to €380,615M and the moderation of NSFR.

Sheet 📈 RATIOS_CAPITAL
A1: BNP PARIBAS — CAPITAL ADEQUACY RATIOS
A2: FY 2022–FY 2024 | CRD VI / CRR3 | ECB SSM framework
A3: Source: BNP Paribas annual results and Pillar 3 disclosures | Capital values in €M
A4: BNP Paribas reported capital ratios above the stated comparison levels across the period. FY2024 CET1 was 12.87% and leverage 4.62%. These are analytical regulatory references only; no BNP-specific SREP threshold or complete applicable requirement is asserted.
A6: REGULATORY CAPITAL SCORECARD
A7: RATIO | B7: CRR3 / ECB DEFINITION | C7: FY 2022 | D7: FY 2023 | E7: FY 2024 | F7: TREND | G7: REGULATORY REFERENCE USED | H7: SIGNAL
A8: Common Equity Tier 1 (CET1) | B8: CET1 capital / total RWA | C8: 0.1233 | D8: 0.132 | E8: 0.1287 | F8: ↗↘ | G8: Analytical comparison only | H8: No SREP threshold asserted
A9: Tier 1 Ratio | B9: Tier 1 capital / total RWA | C9: 0.1389 | D9: 0.1528 | E9: 0.1493 | F9: ↗↘ | G9: 10.5% base reference | H9: Above stated base reference
A10: Total Capital Ratio | B10: Total capital / total RWA | C10: 0.1619 | D10: 0.173 | E10: 0.1713 | F10: ↗↘ | G10: 12.5% base reference | H10: Above stated base reference
A11: Leverage Ratio | B11: Tier 1 capital / total exposure measure | C11: 0.0436 | D11: 0.0458 | E11: 0.0462 | F11: ↗ | G11: 3.0% leverage reference | H11: Above stated base reference
A14: CAPITAL STRUCTURE & RWA
A15: COMPONENT (€M) | B15: FY 2022 | C15: FY 2023 | D15: FY 2024 | E15: Δ€M 22→23 | F15: Δ€M 23→24 | G15: FY2024 SIGNAL
A16: CET1 Capital | B16: 91828 | C16: 92857 | D16: 98128 | E16: =C16-B16 -> 1029 | F16: =D16-C16 -> 5271 | G16: Growing
A17: Additional Tier 1 (AT1 / CoCo) | B17: 11616 | C17: 14644 | D17: 15640 | E17: =C17-B17 -> 3028 | F17: =D17-C17 -> 996 | G17: Growing
A18: Tier 1 Capital | B18: 103445 | C18: 107501 | D18: 113768 | E18: =C18-B18 -> 4056 | F18: =D18-C18 -> 6267 | G18: Growing
A19: Tier 2 Capital | B19: 17117 | C19: 14243 | D19: 16813 | E19: =C19-B19 -> -2874 | F19: =D19-C19 -> 2570 | G19: Recovered
A20: Total Capital | B20: =B18+B19 -> 120562 | C20: =C18+C19 -> 121744 | D20: =D18+D19 -> 130581 | E20: =C20-B20 -> 1182 | F20: =D20-C20 -> 8837 | G20: Record level
A21: Risk-Weighted Assets | B21: 744851 | C21: 703694 | D21: 762247 | E21: =C21-B21 -> -41157 | F21: =D21-C21 -> 58553 | G21: Higher intensity
A22: Credit RWA | B22: 579635 | C22: 535141 | D22: 579602 | E22: =C22-B22 -> -44494 | F22: =D22-C22 -> 44461 | G22: Recovered
A23: Market RWA | B23: 25543 | C23: 28783 | D23: 28123 | E23: =C23-B23 -> 3240 | F23: =D23-C23 -> -660 | G23: Stable
A24: Operational RWA | B24: 61656 | C24: 58897 | D24: 64964 | E24: =C24-B24 -> -2759 | F24: =D24-C24 -> 6067 | G24: Increased
A27: FY2024 CAPITAL COMPARISON
A28: METRIC | B28: FY2024 RATIO | C28: REFERENCE | D28: HEADROOM (pp) | E28: STATUS
A29: CET1 | B29: 0.1287 | C29: No SREP threshold asserted | D29: n/a | E29: REFERENCE ONLY
A30: Tier 1 | B30: =E9 -> 0.1493 | C30: 0.105 | D30: =B30-C30 -> 0.0443 | E30: =IF(D30>0,"PASS","CHECK") -> PASS
A31: Total Capital | B31: =E10 -> 0.1713 | C31: 0.125 | D31: =B31-C31 -> 0.0463 | E31: =IF(D31>0,"PASS","CHECK") -> PASS
A32: Leverage | B32: =E11 -> 0.0462 | C32: 0.03 | D32: =B32-C32 -> 0.0162 | E32: =IF(D32>0,"PASS","CHECK") -> PASS
A34: MANAGEMENT TAKEAWAY
A35: Capital generation remained strong, with CET1 capital reaching €98,128M and total capital €130,581M in FY2024. RWA increased to €762,247M, moderating ratios from FY2023 peaks; reported ratios remained above the stated base references used in this workbook, and leverage continued to improve.

Sheet 📈 RATIOS_ASSET_QUALITY
A1: BNP PARIBAS — ASSET QUALITY RATIOS
A2: FY 2022–FY 2024 | IFRS 9 ECL | EBA NPL definition
A3: Source: BNP Paribas Pillar 3 and annual-results credit-risk disclosures | Monetary values in €M
A4: Credit quality improved over the period: the NPL ratio declined to 1.6%, Stage 1 and Stage 2 ECL balances fell, and total impairment reduced to €17,181M. Coverage remained adequate at 69.7%, although its gradual decline is a watchpoint.
A6: ASSET QUALITY SCORECARD
A7: METRIC | B7: EBA / IFRS 9 DEFINITION | C7: FY 2022 Restated | D7: FY 2023 | E7: FY 2024 | F7: TREND | G7: TARGET / BENCHMARK | H7: SIGNAL
A8: Non-Performing Loan Ratio | B8: 90+ days past due or unlikely to pay without collateral | C8: 0.017 | D8: 0.017 | E8: 0.016 | F8: ↘ | G8: ECB Q2 2024 aggregate: 2.30% | H8: Better than EU average
A9: Coverage Ratio | B9: Loan-loss allowances / gross Stage 3 exposure | C9: 0.725 | D9: 0.717 | E9: 0.697 | F9: ↘ | G9: >50%; higher is stronger | H9: Adequate; declining
A10: Cost of Risk (€M) | B10: BNP-reported Cost of Risk for the period | C10: ='📄 INCOME_STATEMENT'!B27 -> 3003 | D10: ='📄 INCOME_STATEMENT'!C27 -> 2907 | E10: ='📄 INCOME_STATEMENT'!D27 -> 2999 | F10: ↗↘ | G10: Reported Cost of Risk | H10: Standard definition; +3.2% in FY2024
A11: Cost of Risk (bps) | B11: BNP-reported Cost of Risk in basis points | C11: ='📄 INCOME_STATEMENT'!B49 -> 31 | D11: ='📄 INCOME_STATEMENT'!C49 -> 32 | E11: ='📄 INCOME_STATEMENT'!D49 -> 33 | F11: ↗ | G11: ECB Q2 2024 aggregate: 47 bps | H11: Below ECB Q2 2024 sector reference
A12: Stage 1 ECL (€M) | B12: 12-month expected credit losses | C12: 2035 | D12: 1938 | E12: 1785 | F12: ↘ | G12: Lower performing ECL | H12: Improving
A13: Stage 2 ECL (€M) | B13: Lifetime ECL for increased credit risk | C13: 2860 | D13: 2416 | E13: 1939 | F13: ↘ | G13: Rising balance is warning | H13: Improving
A14: Stage 3 Allowance (€M) | B14: Allowance on doubtful / non-performing assets | C14: 13616 | D14: 13361 | E14: 13457 | F14: → | G14: Stable coverage support | H14: Stable
A15: Total Financial-Asset Impairment (€M) | B15: Stage 1 + Stage 2 + Stage 3 allowances | C15: 18511 | D15: 17715 | E15: 17181 | F15: ↘ | G15: Lower is favourable if quality holds | H15: Improving
A18: IMPAIRMENT MOVEMENT ANALYSIS
A19: COMPONENT (€M) | B19: FY 2022 | C19: FY 2023 | D19: FY 2024 | E19: Δ€M 22→23 | F19: Δ€M 23→24 | G19: FY2024 SIGNAL
A20: Stage 1 ECL | B20: =C12 -> 2035 | C20: =D12 -> 1938 | D20: =E12 -> 1785 | E20: =C20-B20 -> -97 | F20: =D20-C20 -> -153 | G20: Declining
A21: Stage 2 ECL | B21: =C13 -> 2860 | C21: =D13 -> 2416 | D21: =E13 -> 1939 | E21: =C21-B21 -> -444 | F21: =D21-C21 -> -477 | G21: Declining
A22: Stage 3 Allowance | B22: =C14 -> 13616 | C22: =D14 -> 13361 | D22: =E14 -> 13457 | E22: =C22-B22 -> -255 | F22: =D22-C22 -> 96 | G22: Stable
A23: Total Impairment | B23: =C15 -> 18511 | C23: =D15 -> 17715 | D23: =E15 -> 17181 | E23: =C23-B23 -> -796 | F23: =D23-C23 -> -534 | G23: Declining
A26: IFRS 9 STAGING NOTE
A27: Stage 1 represents performing assets subject to 12-month ECL; Stage 2 represents exposures with significantly increased credit risk and lifetime ECL; Stage 3 represents credit-impaired or non-performing exposures.
A30: MANAGEMENT TAKEAWAY
A31: BNP Paribas’ credit-risk profile improved through FY2024, with lower NPLs and falling early-stage ECL balances. Cost of Risk was 33 bps versus the ECB Q2 2024 sector reference of 47 bps; declining coverage warrants continued monitoring.

Sheet 📈 RATIOS_EFFICIENCY
A1: BNP PARIBAS — EFFICIENCY RATIOS
A2: FY 2022–FY 2024 | Operating leverage and cost-efficiency analysis
A3: Analytical comparison: cost-to-income ratio below 66% | Positive operating leverage above 0 pp
A4: Efficiency improved materially in FY2024: NBI grew 6.45%, operating expenses declined 2.46%, and CIR fell to 61.83%. This generated positive operating leverage of 8.91 pp after the FY2023 deterioration.
A6: EFFICIENCY SCORECARD
A7: METRIC | B7: FORMULA / DEFINITION | C7: FY 2022 Restated | D7: FY 2023 | E7: FY 2024 | F7: TREND | G7: COMPARISON | H7: SIGNAL
A8: Cost-to-Income Ratio (CIR) | B8: Total operating expenses / total NBI | C8: ='📄 INCOME_STATEMENT'!B22/'📄 INCOME_STATEMENT'!B15 -> 0.65736298 | D8: ='📄 INCOME_STATEMENT'!C22/'📄 INCOME_STATEMENT'!C15 -> 0.6748049 | E8: ='📄 INCOME_STATEMENT'!D22/'📄 INCOME_STATEMENT'!D15 -> 0.61831623 | F8: ↗↘ | G8: <66.0% | H8: Below comparison in FY2024
A9: CIR vs 66% Comparison (pp) | B9: CIR less 66.0% analytical comparison | C9: =C8-66% -> -0.002637024 | D9: =D8-66% -> 0.0148049 | E9: =E8-66% -> -0.041683766 | F9: ↗↘ | G9: Negative = pass | H9: Below comparison in FY2024
A10: NBI Growth | B10: Current-year NBI / prior-year NBI − 1 | C10: n/a | D10: ='📄 INCOME_STATEMENT'!C15/'📄 INCOME_STATEMENT'!B15-1 -> 0.0097732776 | E10: ='📄 INCOME_STATEMENT'!D15/'📄 INCOME_STATEMENT'!C15-1 -> 0.064459171 | F10: ↗ | G10: Positive growth | H10: Strong FY2024 growth
A11: Operating Expense Growth | B11: Current-year OpEx / prior-year OpEx − 1 | C11: n/a | D11: ='📄 INCOME_STATEMENT'!C22/'📄 INCOME_STATEMENT'!B22-1 -> 0.036565765 | E11: ='📄 INCOME_STATEMENT'!D22/'📄 INCOME_STATEMENT'!C22-1 -> -0.024647887 | F11: ↗↘ | G11: Below NBI growth | H11: Costs declined in FY2024
A12: Operating Leverage (pp) | B12: NBI growth less OpEx growth | C12: n/a | D12: =(D10-D11)*100 -> -2.6792487 | E12: =(E10-E11)*100 -> 8.9107058 | F12: ↗ | G12: >0 pp | H12: Positive in FY2024
A13: Capex / NBI | B13: Capital expenditure / total NBI | C13: 0.0557 | D13: 0.0483 | E13: 0.0437 | F13: ↘ | G13: Efficient reinvestment | H13: Declining intensity
A16: COMPARISON ASSESSMENT
A17: TEST | B17: FY 2022 | C17: FY 2023 | D17: FY 2024 | E17: FY2024 STATUS | F17: COMMENT
A18: CIR below 66% analytical comparison | B18: =C8<66% -> TRUE | C18: =D8<66% -> FALSE | D18: =E8<66% -> TRUE | E18: =IF(D18,"PASS","CHECK") -> PASS | F18: CIR moved below comparison
A19: Operating leverage above 0 pp | B19: ="n/a" -> n/a | C19: =D12>0 -> FALSE | D19: =E12>0 -> TRUE | E19: =IF(D19,"PASS","CHECK") -> PASS | F19: Strong positive leverage
A20: NBI growth exceeds OpEx growth | B20: ="n/a" -> n/a | C20: =D10>D11 -> FALSE | D20: =E10>E11 -> TRUE | E20: =IF(D20,"PASS","CHECK") -> PASS | F20: Revenue outpaced costs
A23: MANAGEMENT TAKEAWAY
A24: FY2024 delivered stronger revenue, lower expenses, positive operating leverage, and a CIR below the workbook’s 66% analytical comparison. The key forward-looking sensitivity is continued NIM pressure and the ability to maintain positive operating leverage.

Sheet 📉 TRENDS_CHARTS
A1: BNP PARIBAS — FINANCIAL TRENDS DASHBOARD
A2: FY 2022 Restated–FY 2024 | Earnings, returns, capital, credit quality, and efficiency
A3: Six verified native Excel charts | Values live-linked to the workbook’s financial statements and ratio schedules
A5: STORY IN BRIEF
A6: FY2024 delivered stronger earnings and efficiency: NBI reached €48,831M, net income rose to €11,688M, and CIR improved to 61.83%. ROE and ROTE continued to rise, CET1 remained strong on an analytical-comparison basis, and the NPL ratio improved to 1.6%. The principal watchpoints are lower NIM, declining NPL coverage, and capital ratios moderating from FY2023 peaks. No BNP-specific SREP threshold is asserted.
A10: TREND CHARTS
A68: KEY FINDINGS
A70: 1. Earnings — FY2024 NBI rose 6.4% and net income attributable to equity holders increased 6.5%.
A71: 2. Returns — ROE and ROTE improved each year, reaching 9.28% and 10.07% in FY2024.
A72: 3. Capital — CET1 closed FY2024 at 12.87%; regulatory references are analytical comparisons only and no BNP-specific SREP threshold is asserted.
A73: 4. Credit — NPL improved to 1.6% versus the 2.3% ECB reference; Cost of Risk increased to 33 bps but remained below the 47 bps sector reference.
A74: 5. Efficiency — CIR improved to 61.83%, below the workbook’s 66% analytical comparison.

Sheet 💧 WATERFALL_NET_INCOME
A1: BNP PARIBAS — NET INCOME WATERFALL
A2: FY 2022 → FY 2023 → FY 2024 | Income-statement driver attribution
A3: All values in €M | Green = positive contribution | Red = negative contribution | Grey = reported net income
A4: Net income increased from €9,848M in restated FY2022 to €11,688M in FY2024, an 8.9% two-year CAGR. Standard Cost of Risk improved in FY2023 and increased slightly in FY2024, while other net risk losses declined from €775M to €202M.
A6: NET INCOME BRIDGE CHART
A29: FY 2022 → FY 2023 DRIVER TABLE
A30: DRIVER | B30: CHANGE (€M) | C30: RUNNING BALANCE | D30: DIRECTION | E30: SOURCE / INTERPRETATION | F30: DISPLAY LABEL
A31: Opening net income FY2022 (restated) | B31: ='📄 INCOME_STATEMENT'!B44 -> 9848 | C31: =B31 -> 9848 | D31: Restated | E31: Income statement | F31: =IF(OR(D31="Reported",D31="Restated"),"€"&TEXT(B31,"#,##0")&"M",IF(B31>=0,"+€","−€")&TEXT(ABS(B31),"#,##0")&"M") -> €9,848M
A32: Net Interest Income | B32: ='📄 INCOME_STATEMENT'!C10-'📄 INCOME_STATEMENT'!B10 -> -1875 | C32: =C31+B32 -> 7973 | D32: =IF(B32>0,"Positive",IF(B32<0,"Negative","Neutral")) -> Negative | E32: NII movement | F32: =IF(OR(D32="Reported",D32="Restated"),"€"&TEXT(B32,"#,##0")&"M",IF(B32>=0,"+€","−€")&TEXT(ABS(B32),"#,##0")&"M") -> −€1,875M
A33: Fee & Commission Income | B33: ='📄 INCOME_STATEMENT'!C11-'📄 INCOME_STATEMENT'!B11 -> -344 | C33: =C32+B33 -> 7629 | D33: =IF(B33>0,"Positive",IF(B33<0,"Negative","Neutral")) -> Negative | E33: Fees movement | F33: =IF(OR(D33="Reported",D33="Restated"),"€"&TEXT(B33,"#,##0")&"M",IF(B33>=0,"+€","−€")&TEXT(ABS(B33),"#,##0")&"M") -> −€344M
A34: Trading Income | B34: ='📄 INCOME_STATEMENT'!C12-'📄 INCOME_STATEMENT'!B12 -> 994 | C34: =C33+B34 -> 8623 | D34: =IF(B34>0,"Positive",IF(B34<0,"Negative","Neutral")) -> Positive | E34: Trading movement | F34: =IF(OR(D34="Reported",D34="Restated"),"€"&TEXT(B34,"#,##0")&"M",IF(B34>=0,"+€","−€")&TEXT(ABS(B34),"#,##0")&"M") -> +€994M
A35: Other operating activities | B35: ='📄 INCOME_STATEMENT'!C13-'📄 INCOME_STATEMENT'!B13 -> 1253 | C35: =C34+B35 -> 9876 | D35: =IF(B35>0,"Positive",IF(B35<0,"Negative","Neutral")) -> Positive | E35: Other activities movement | F35: =IF(OR(D35="Reported",D35="Restated"),"€"&TEXT(B35,"#,##0")&"M",IF(B35>=0,"+€","−€")&TEXT(ABS(B35),"#,##0")&"M") -> +€1,253M
A36: Unallocated NBI components | B36: =('📄 INCOME_STATEMENT'!C15-SUM('📄 INCOME_STATEMENT'!C10:C13))-('📄 INCOME_STATEMENT'!B15-SUM('📄 INCOME_STATEMENT'!B10:B13)) -> 416 | C36: =C35+B36 -> 10292 | D36: =IF(B36>0,"Positive",IF(B36<0,"Negative","Neutral")) -> Positive | E36: NBI reconciliation | F36: =IF(OR(D36="Reported",D36="Restated"),"€"&TEXT(B36,"#,##0")&"M",IF(B36>=0,"+€","−€")&TEXT(ABS(B36),"#,##0")&"M") -> +€416M
A37: Operating expenses effect | B37: =-('📄 INCOME_STATEMENT'!C22-'📄 INCOME_STATEMENT'!B22) -> -1092 | C37: =C36+B37 -> 9200 | D37: =IF(B37>0,"Positive",IF(B37<0,"Negative","Neutral")) -> Negative | E37: Lower expenses are positive | F37: =IF(OR(D37="Reported",D37="Restated"),"€"&TEXT(B37,"#,##0")&"M",IF(B37>=0,"+€","−€")&TEXT(ABS(B37),"#,##0")&"M") -> −€1,092M
A38: Cost of Risk effect | B38: =-('📄 INCOME_STATEMENT'!C27-'📄 INCOME_STATEMENT'!B27) -> 96 | C38: =C37+B38 -> 9296 | D38: =IF(B38>0,"Positive",IF(B38<0,"Negative","Neutral")) -> Positive | E38: Lower Cost of Risk is positive | F38: =IF(OR(D38="Reported",D38="Restated"),"€"&TEXT(B38,"#,##0")&"M",IF(B38>=0,"+€","−€")&TEXT(ABS(B38),"#,##0")&"M") -> +€96M
A39: Other net losses for risk on financial instruments effect | B39: =-('📄 INCOME_STATEMENT'!C28-'📄 INCOME_STATEMENT'!B28) -> -775 | C39: =C38+B39 -> 8521 | D39: =IF(B39>0,"Positive",IF(B39<0,"Negative","Neutral")) -> Negative | E39: Lower other net risk losses are positive | F39: =IF(OR(D39="Reported",D39="Restated"),"€"&TEXT(B39,"#,##0")&"M",IF(B39>=0,"+€","−€")&TEXT(ABS(B39),"#,##0")&"M") -> −€775M
A40: Non-operating items | B40: =('📄 INCOME_STATEMENT'!C33+'📄 INCOME_STATEMENT'!C34+'📄 INCOME_STATEMENT'!C35)-('📄 INCOME_STATEMENT'!B33+'📄 INCOME_STATEMENT'!B34+'📄 INCOME_STATEMENT'!B35) -> -162 | C40: =C39+B40 -> 8359 | D40: =IF(B40>0,"Positive",IF(B40<0,"Negative","Neutral")) -> Negative | E40: Non-operating items | F40: =IF(OR(D40="Reported",D40="Restated"),"€"&TEXT(B40,"#,##0")&"M",IF(B40>=0,"+€","−€")&TEXT(ABS(B40),"#,##0")&"M") -> −€162M
A41: Tax effect | B41: =-('📄 INCOME_STATEMENT'!C39-'📄 INCOME_STATEMENT'!B39) -> 387 | C41: =C40+B41 -> 8746 | D41: =IF(B41>0,"Positive",IF(B41<0,"Negative","Neutral")) -> Positive | E41: Lower tax is positive | F41: =IF(OR(D41="Reported",D41="Restated"),"€"&TEXT(B41,"#,##0")&"M",IF(B41>=0,"+€","−€")&TEXT(ABS(B41),"#,##0")&"M") -> +€387M
A42: Discontinued operations & minority interests | B42: =('📄 INCOME_STATEMENT'!C44-'📄 INCOME_STATEMENT'!B44)-SUM(B32:B41) -> 2229 | C42: =C41+B42 -> 10975 | D42: =IF(B42>0,"Positive",IF(B42<0,"Negative","Neutral")) -> Positive | E42: Reconciliation item | F42: =IF(OR(D42="Reported",D42="Restated"),"€"&TEXT(B42,"#,##0")&"M",IF(B42>=0,"+€","−€")&TEXT(ABS(B42),"#,##0")&"M") -> +€2,229M
A43: Closing net income FY2023 | B43: ='📄 INCOME_STATEMENT'!C44 -> 10975 | C43: =B43 -> 10975 | D43: Reported | E43: Income statement | F43: =IF(OR(D43="Reported",D43="Restated"),"€"&TEXT(B43,"#,##0")&"M",IF(B43>=0,"+€","−€")&TEXT(ABS(B43),"#,##0")&"M") -> €10,975M
A46: Opening net income FY2023 | B46: ='📄 INCOME_STATEMENT'!C44 -> 10975 | C46: =B46 -> 10975 | D46: Reported | E46: Income statement | F46: =IF(D46="Reported","€"&TEXT(B46,"#,##0")&"M",IF(B46>=0,"+€","−€")&TEXT(ABS(B46),"#,##0")&"M") -> €10,975M
A47: Net Interest Income | B47: ='📄 INCOME_STATEMENT'!D10-'📄 INCOME_STATEMENT'!C10 -> 466 | C47: =C46+B47 -> 11441 | D47: =IF(B47>0,"Positive",IF(B47<0,"Negative","Neutral")) -> Positive | E47: NII movement | F47: =IF(D47="Reported","€"&TEXT(B47,"#,##0")&"M",IF(B47>=0,"+€","−€")&TEXT(ABS(B47),"#,##0")&"M") -> +€466M
A48: Fee & Commission Income | B48: ='📄 INCOME_STATEMENT'!D11-'📄 INCOME_STATEMENT'!C11 -> 880 | C48: =C47+B48 -> 12321 | D48: =IF(B48>0,"Positive",IF(B48<0,"Negative","Neutral")) -> Positive | E48: Fees movement | F48: =IF(D48="Reported","€"&TEXT(B48,"#,##0")&"M",IF(B48>=0,"+€","−€")&TEXT(ABS(B48),"#,##0")&"M") -> +€880M
A49: Trading Income | B49: ='📄 INCOME_STATEMENT'!D12-'📄 INCOME_STATEMENT'!C12 -> 1223 | C49: =C48+B49 -> 13544 | D49: =IF(B49>0,"Positive",IF(B49<0,"Negative","Neutral")) -> Positive | E49: Trading movement | F49: =IF(D49="Reported","€"&TEXT(B49,"#,##0")&"M",IF(B49>=0,"+€","−€")&TEXT(ABS(B49),"#,##0")&"M") -> +€1,223M
A50: Other operating activities | B50: ='📄 INCOME_STATEMENT'!D13-'📄 INCOME_STATEMENT'!C13 -> 142 | C50: =C49+B50 -> 13686 | D50: =IF(B50>0,"Positive",IF(B50<0,"Negative","Neutral")) -> Positive | E50: Other activities movement | F50: =IF(D50="Reported","€"&TEXT(B50,"#,##0")&"M",IF(B50>=0,"+€","−€")&TEXT(ABS(B50),"#,##0")&"M") -> +€142M
A51: Unallocated NBI components | B51: =('📄 INCOME_STATEMENT'!D15-SUM('📄 INCOME_STATEMENT'!D10:D13))-('📄 INCOME_STATEMENT'!C15-SUM('📄 INCOME_STATEMENT'!C10:C13)) -> 246 | C51: =C50+B51 -> 13932 | D51: =IF(B51>0,"Positive",IF(B51<0,"Negative","Neutral")) -> Positive | E51: NBI reconciliation | F51: =IF(D51="Reported","€"&TEXT(B51,"#,##0")&"M",IF(B51>=0,"+€","−€")&TEXT(ABS(B51),"#,##0")&"M") -> +€246M
A52: Operating expenses effect | B52: =-('📄 INCOME_STATEMENT'!D22-'📄 INCOME_STATEMENT'!C22) -> 763 | C52: =C51+B52 -> 14695 | D52: =IF(B52>0,"Positive",IF(B52<0,"Negative","Neutral")) -> Positive | E52: Lower expenses are positive | F52: =IF(D52="Reported","€"&TEXT(B52,"#,##0")&"M",IF(B52>=0,"+€","−€")&TEXT(ABS(B52),"#,##0")&"M") -> +€763M
A53: Cost of Risk effect | B53: =-('📄 INCOME_STATEMENT'!D27-'📄 INCOME_STATEMENT'!C27) -> -92 | C53: =C52+B53 -> 14603 | D53: =IF(B53>0,"Positive",IF(B53<0,"Negative","Neutral")) -> Negative | E53: Lower Cost of Risk is positive | F53: =IF(D53="Reported","€"&TEXT(B53,"#,##0")&"M",IF(B53>=0,"+€","−€")&TEXT(ABS(B53),"#,##0")&"M") -> −€92M
A54: Other net losses for risk on financial instruments effect | B54: =-('📄 INCOME_STATEMENT'!D28-'📄 INCOME_STATEMENT'!C28) -> 573 | C54: =C53+B54 -> 15176 | D54: =IF(B54>0,"Positive",IF(B54<0,"Negative","Neutral")) -> Positive | E54: Lower other net risk losses are positive | F54: =IF(D54="Reported","€"&TEXT(B54,"#,##0")&"M",IF(B54>=0,"+€","−€")&TEXT(ABS(B54),"#,##0")&"M") -> +€573M
A55: Non-operating items | B55: =('📄 INCOME_STATEMENT'!D33+'📄 INCOME_STATEMENT'!D34+'📄 INCOME_STATEMENT'!D35)-('📄 INCOME_STATEMENT'!C33+'📄 INCOME_STATEMENT'!C34+'📄 INCOME_STATEMENT'!C35) -> 262 | C55: =C54+B55 -> 15438 | D55: =IF(B55>0,"Positive",IF(B55<0,"Negative","Neutral")) -> Positive | E55: Non-operating items | F55: =IF(D55="Reported","€"&TEXT(B55,"#,##0")&"M",IF(B55>=0,"+€","−€")&TEXT(ABS(B55),"#,##0")&"M") -> +€262M
A56: Tax effect | B56: =-('📄 INCOME_STATEMENT'!D39-'📄 INCOME_STATEMENT'!C39) -> -735 | C56: =C55+B56 -> 14703 | D56: =IF(B56>0,"Positive",IF(B56<0,"Negative","Neutral")) -> Negative | E56: Lower tax is positive | F56: =IF(D56="Reported","€"&TEXT(B56,"#,##0")&"M",IF(B56>=0,"+€","−€")&TEXT(ABS(B56),"#,##0")&"M") -> −€735M
A57: Discontinued operations & minority interests | B57: =('📄 INCOME_STATEMENT'!D44-'📄 INCOME_STATEMENT'!C44)-SUM(B47:B56) -> -3015 | C57: =C56+B57 -> 11688 | D57: =IF(B57>0,"Positive",IF(B57<0,"Negative","Neutral")) -> Negative | E57: Reconciliation item | F57: =IF(D57="Reported","€"&TEXT(B57,"#,##0")&"M",IF(B57>=0,"+€","−€")&TEXT(ABS(B57),"#,##0")&"M") -> −€3,015M
A58: Closing net income FY2024 | B58: ='📄 INCOME_STATEMENT'!D44 -> 11688 | C58: =B58 -> 11688 | D58: Reported | E58: Income statement | F58: =IF(D58="Reported","€"&TEXT(B58,"#,##0")&"M",IF(B58>=0,"+€","−€")&TEXT(ABS(B58),"#,##0")&"M") -> €11,688M
A61: FY2022→FY2023 reconciliation | B61: =C42-B43 -> 0 | C61: =IF(B61=0,"PASS","CHECK") -> PASS
A62: FY2023→FY2024 reconciliation | B62: =C57-B58 -> 0 | C62: =IF(B62=0,"PASS","CHECK") -> PASS
A65: FY2024 earnings growth was supported by broad revenue recovery and lower operating expenses. Standard Cost of Risk increased by €92M, but other net risk losses improved by €573M, making the combined risk-charge contribution positive. Discontinued operations and minority interests remained the largest reconciliation offset.

Sheet 🔗CHART_SOURCE
A1: BNP PARIBAS — CHART SOURCES
A2: FY 2022–FY 2024 | Live source ranges for the financial trends dashboard
A3: Edit the linked financial and ratio sheets; these values and the dashboard charts recalculate automatically.
A5: EARNINGS
A6: Series | B6: FY 2022 Restated | C6: FY 2023 | D6: FY 2024
A7: Net Banking Income (€M) | B7: ='📄 INCOME_STATEMENT'!B15 -> 45430 | C7: ='📄 INCOME_STATEMENT'!C15 -> 45874 | D7: ='📄 INCOME_STATEMENT'!D15 -> 48831
A8: Net Income — Group Share (€M) | B8: ='📄 INCOME_STATEMENT'!B44 -> 9848 | C8: ='📄 INCOME_STATEMENT'!C44 -> 10975 | D8: ='📄 INCOME_STATEMENT'!D44 -> 11688
A10: RETURNS
A11: Series | B11: FY 2022 | C11: FY 2023 | D11: FY 2024
A12: ROE | B12: ='📈 RATIOS_PROFITABILITY'!C8 -> 0.082367652 | C12: ='📈 RATIOS_PROFITABILITY'!D8 -> 0.089599517 | D12: ='📈 RATIOS_PROFITABILITY'!E8 -> 0.092806467
A13: ROTE | B13: ='📈 RATIOS_PROFITABILITY'!C9 -> 0.089017848 | C13: ='📈 RATIOS_PROFITABILITY'!D9 -> 0.097036304 | D13: ='📈 RATIOS_PROFITABILITY'!E9 -> 0.10065189
A15: CAPITAL
A16: Series | B16: FY 2022 | C16: FY 2023 | D16: FY 2024
A17: CET1 Ratio | B17: ='📈 RATIOS_CAPITAL'!C8 -> 0.1233 | C17: ='📈 RATIOS_CAPITAL'!D8 -> 0.132 | D17: ='📈 RATIOS_CAPITAL'!E8 -> 0.1287
A20: CREDIT QUALITY
A21: Series | B21: FY 2022 Restated | C21: FY 2023 | D21: FY 2024
A22: NPL Ratio | B22: ='📈 RATIOS_ASSET_QUALITY'!C8 -> 0.017 | C22: ='📈 RATIOS_ASSET_QUALITY'!D8 -> 0.017 | D22: ='📈 RATIOS_ASSET_QUALITY'!E8 -> 0.016
A23: Cost of Risk (bps) | B23: ='📈 RATIOS_ASSET_QUALITY'!C11 -> 31 | C23: ='📈 RATIOS_ASSET_QUALITY'!D11 -> 32 | D23: ='📈 RATIOS_ASSET_QUALITY'!E11 -> 33
A24: Cost of Risk (€M) | B24: ='📄 INCOME_STATEMENT'!B27 -> 3003 | C24: ='📄 INCOME_STATEMENT'!C27 -> 2907 | D24: ='📄 INCOME_STATEMENT'!D27 -> 2999
A25: ECB Q2 2024 NPL Reference | B25: 0.023 | C25: 0.023 | D25: 0.023
A26: EFFICIENCY
A27: Series | B27: FY 2022 Restated | C27: FY 2023 | D27: FY 2024
A28: Cost-to-Income Ratio | B28: ='📈 RATIOS_EFFICIENCY'!C8 -> 0.65736298 | C28: ='📈 RATIOS_EFFICIENCY'!D8 -> 0.6748049 | D28: ='📈 RATIOS_EFFICIENCY'!E8 -> 0.61831623
A29: Analytical Comparison (66%) | B29: 0.66 | C29: 0.66 | D29: 0.66
A32: WATERFALL — NET INCOME BRIDGE | G32: NATIVE WATERFALL SOURCE | J32: WATERFALL HELPERS
A33: Category | B33: Base | C33: Positive | D33: Negative | E33: Total | G33: Driver | H33: Value (€M) | J33: Running Balance | K33: Base | L33: Increase | M33: Decrease | N33: Total
A34: FY 2022 | B34: =0 -> 0 | C34: =0 -> 0 | D34: =0 -> 0 | E34: ='💧 WATERFALL_NET_INCOME'!B31 -> 9848 | G34: ='💧 WATERFALL_NET_INCOME'!A31 -> Opening net income FY2022 (restated) | H34: ='💧 WATERFALL_NET_INCOME'!B31 -> 9848 | J34: =H34 -> 9848 | K34: =0 -> 0 | L34: =0 -> 0 | M34: =0 -> 0 | N34: =H34 -> 9848
A35: NII 22→23 | B35: =MIN('💧 WATERFALL_NET_INCOME'!C31,'💧 WATERFALL_NET_INCOME'!C32) -> 7973 | C35: =IF('💧 WATERFALL_NET_INCOME'!B32>0,ABS('💧 WATERFALL_NET_INCOME'!B32),0) -> 0 | D35: =IF('💧 WATERFALL_NET_INCOME'!B32<0,ABS('💧 WATERFALL_NET_INCOME'!B32),0) -> 1875 | E35: =0 -> 0 | G35: ='💧 WATERFALL_NET_INCOME'!A32 -> Net Interest Income | H35: ='💧 WATERFALL_NET_INCOME'!B32 -> -1875 | J35: =J34+H35 -> 7973 | K35: =IF(H35>=0,J34,J35) -> 7973 | L35: =MAX(H35,0) -> 0 | M35: =MAX(-H35,0) -> 1875 | N35: =0 -> 0
A36: Fees 22→23 | B36: =MIN('💧 WATERFALL_NET_INCOME'!C32,'💧 WATERFALL_NET_INCOME'!C33) -> 7629 | C36: =IF('💧 WATERFALL_NET_INCOME'!B33>0,ABS('💧 WATERFALL_NET_INCOME'!B33),0) -> 0 | D36: =IF('💧 WATERFALL_NET_INCOME'!B33<0,ABS('💧 WATERFALL_NET_INCOME'!B33),0) -> 344 | E36: =0 -> 0 | G36: ='💧 WATERFALL_NET_INCOME'!A33 -> Fee & Commission Income | H36: ='💧 WATERFALL_NET_INCOME'!B33 -> -344 | J36: =J35+H36 -> 7629 | K36: =IF(H36>=0,J35,J36) -> 7629 | L36: =MAX(H36,0) -> 0 | M36: =MAX(-H36,0) -> 344 | N36: =0 -> 0
A37: Trading 22→23 | B37: =MIN('💧 WATERFALL_NET_INCOME'!C33,'💧 WATERFALL_NET_INCOME'!C34) -> 7629 | C37: =IF('💧 WATERFALL_NET_INCOME'!B34>0,ABS('💧 WATERFALL_NET_INCOME'!B34),0) -> 994 | D37: =IF('💧 WATERFALL_NET_INCOME'!B34<0,ABS('💧 WATERFALL_NET_INCOME'!B34),0) -> 0 | E37: =0 -> 0 | G37: ='💧 WATERFALL_NET_INCOME'!A34 -> Trading Income | H37: ='💧 WATERFALL_NET_INCOME'!B34 -> 994 | J37: =J36+H37 -> 8623 | K37: =IF(H37>=0,J36,J37) -> 7629 | L37: =MAX(H37,0) -> 994 | M37: =MAX(-H37,0) -> 0 | N37: =0 -> 0
A38: Other NBI 22→23 | B38: =MIN('💧 WATERFALL_NET_INCOME'!C34,'💧 WATERFALL_NET_INCOME'!C35) -> 8623 | C38: =IF('💧 WATERFALL_NET_INCOME'!B35>0,ABS('💧 WATERFALL_NET_INCOME'!B35),0) -> 1253 | D38: =IF('💧 WATERFALL_NET_INCOME'!B35<0,ABS('💧 WATERFALL_NET_INCOME'!B35),0) -> 0 | E38: =0 -> 0 | G38: ='💧 WATERFALL_NET_INCOME'!A35 -> Other operating activities | H38: ='💧 WATERFALL_NET_INCOME'!B35 -> 1253 | J38: =J37+H38 -> 9876 | K38: =IF(H38>=0,J37,J38) -> 8623 | L38: =MAX(H38,0) -> 1253 | M38: =MAX(-H38,0) -> 0 | N38: =0 -> 0
A39: OpEx 22→23 | B39: =MIN('💧 WATERFALL_NET_INCOME'!C35,'💧 WATERFALL_NET_INCOME'!C36) -> 9876 | C39: =IF('💧 WATERFALL_NET_INCOME'!B36>0,ABS('💧 WATERFALL_NET_INCOME'!B36),0) -> 416 | D39: =IF('💧 WATERFALL_NET_INCOME'!B36<0,ABS('💧 WATERFALL_NET_INCOME'!B36),0) -> 0 | E39: =0 -> 0 | G39: ='💧 WATERFALL_NET_INCOME'!A36 -> Unallocated NBI components | H39: ='💧 WATERFALL_NET_INCOME'!B36 -> 416 | J39: =J38+H39 -> 10292 | K39: =IF(H39>=0,J38,J39) -> 9876 | L39: =MAX(H39,0) -> 416 | M39: =MAX(-H39,0) -> 0 | N39: =0 -> 0
A40: Cost of Risk 22→23 | B40: =MIN('💧 WATERFALL_NET_INCOME'!C36,'💧 WATERFALL_NET_INCOME'!C37) -> 9200 | C40: =IF('💧 WATERFALL_NET_INCOME'!B37>0,ABS('💧 WATERFALL_NET_INCOME'!B37),0) -> 0 | D40: =IF('💧 WATERFALL_NET_INCOME'!B37<0,ABS('💧 WATERFALL_NET_INCOME'!B37),0) -> 1092 | E40: =0 -> 0 | G40: ='💧 WATERFALL_NET_INCOME'!A37 -> Operating expenses effect | H40: ='💧 WATERFALL_NET_INCOME'!B37 -> -1092 | J40: =J39+H40 -> 9200 | K40: =IF(H40>=0,J39,J40) -> 9200 | L40: =MAX(H40,0) -> 0 | M40: =MAX(-H40,0) -> 1092 | N40: =0 -> 0
A41: Non-op 22→23 | B41: =MIN('💧 WATERFALL_NET_INCOME'!C37,'💧 WATERFALL_NET_INCOME'!C38) -> 9200 | C41: =IF('💧 WATERFALL_NET_INCOME'!B38>0,ABS('💧 WATERFALL_NET_INCOME'!B38),0) -> 96 | D41: =IF('💧 WATERFALL_NET_INCOME'!B38<0,ABS('💧 WATERFALL_NET_INCOME'!B38),0) -> 0 | E41: =0 -> 0 | G41: ='💧 WATERFALL_NET_INCOME'!A38 -> Cost of Risk effect | H41: ='💧 WATERFALL_NET_INCOME'!B38 -> 96 | J41: =J40+H41 -> 9296 | K41: =IF(H41>=0,J40,J41) -> 9200 | L41: =MAX(H41,0) -> 96 | M41: =MAX(-H41,0) -> 0 | N41: =0 -> 0
A42: Tax 22→23 | B42: =MIN('💧 WATERFALL_NET_INCOME'!C38,'💧 WATERFALL_NET_INCOME'!C39) -> 8521 | C42: =IF('💧 WATERFALL_NET_INCOME'!B39>0,ABS('💧 WATERFALL_NET_INCOME'!B39),0) -> 0 | D42: =IF('💧 WATERFALL_NET_INCOME'!B39<0,ABS('💧 WATERFALL_NET_INCOME'!B39),0) -> 775 | E42: =0 -> 0 | G42: ='💧 WATERFALL_NET_INCOME'!A39 -> Other net losses for risk on financial instruments effect | H42: ='💧 WATERFALL_NET_INCOME'!B39 -> -775 | J42: =J41+H42 -> 8521 | K42: =IF(H42>=0,J41,J42) -> 8521 | L42: =MAX(H42,0) -> 0 | M42: =MAX(-H42,0) -> 775 | N42: =0 -> 0
A43: Disc. ops / NCI 22→23 | B43: =MIN('💧 WATERFALL_NET_INCOME'!C39,'💧 WATERFALL_NET_INCOME'!C40) -> 8359 | C43: =IF('💧 WATERFALL_NET_INCOME'!B40>0,ABS('💧 WATERFALL_NET_INCOME'!B40),0) -> 0 | D43: =IF('💧 WATERFALL_NET_INCOME'!B40<0,ABS('💧 WATERFALL_NET_INCOME'!B40),0) -> 162 | E43: =0 -> 0 | G43: ='💧 WATERFALL_NET_INCOME'!A40 -> Non-operating items | H43: ='💧 WATERFALL_NET_INCOME'!B40 -> -162 | J43: =J42+H43 -> 8359 | K43: =IF(H43>=0,J42,J43) -> 8359 | L43: =MAX(H43,0) -> 0 | M43: =MAX(-H43,0) -> 162 | N43: =0 -> 0
A44: FY 2023 | B44: =0 -> 0 | C44: =0 -> 0 | D44: =0 -> 0 | E44: ='💧 WATERFALL_NET_INCOME'!B41 -> 387 | G44: ='💧 WATERFALL_NET_INCOME'!A41 -> Tax effect | H44: ='💧 WATERFALL_NET_INCOME'!B41 -> 387 | J44: =J43+H44 -> 8746 | K44: =IF(H44>=0,J43,J44) -> 8359 | L44: =MAX(H44,0) -> 387 | M44: =MAX(-H44,0) -> 0 | N44: =0 -> 0
A45: NII 23→24 | B45: =MIN('💧 WATERFALL_NET_INCOME'!C46,'💧 WATERFALL_NET_INCOME'!C47) -> 10975 | C45: =IF('💧 WATERFALL_NET_INCOME'!B47>0,ABS('💧 WATERFALL_NET_INCOME'!B47),0) -> 466 | D45: =IF('💧 WATERFALL_NET_INCOME'!B47<0,ABS('💧 WATERFALL_NET_INCOME'!B47),0) -> 0 | E45: =0 -> 0 | G45: ='💧 WATERFALL_NET_INCOME'!A42 -> Discontinued operations & minority interests | H45: ='💧 WATERFALL_NET_INCOME'!B42 -> 2229 | J45: =J44+H45 -> 10975 | K45: =IF(H45>=0,J44,J45) -> 8746 | L45: =MAX(H45,0) -> 2229 | M45: =MAX(-H45,0) -> 0 | N45: =0 -> 0
A46: Fees 23→24 | B46: =MIN('💧 WATERFALL_NET_INCOME'!C47,'💧 WATERFALL_NET_INCOME'!C48) -> 11441 | C46: =IF('💧 WATERFALL_NET_INCOME'!B48>0,ABS('💧 WATERFALL_NET_INCOME'!B48),0) -> 880 | D46: =IF('💧 WATERFALL_NET_INCOME'!B48<0,ABS('💧 WATERFALL_NET_INCOME'!B48),0) -> 0 | E46: =0 -> 0 | G46: ='💧 WATERFALL_NET_INCOME'!A43 -> Closing net income FY2023 | H46: ='💧 WATERFALL_NET_INCOME'!B43 -> 10975 | J46: =H46 -> 10975 | K46: =0 -> 0 | L46: =0 -> 0 | M46: =0 -> 0 | N46: =H46 -> 10975
A47: Trading 23→24 | B47: =MIN('💧 WATERFALL_NET_INCOME'!C48,'💧 WATERFALL_NET_INCOME'!C49) -> 12321 | C47: =IF('💧 WATERFALL_NET_INCOME'!B49>0,ABS('💧 WATERFALL_NET_INCOME'!B49),0) -> 1223 | D47: =IF('💧 WATERFALL_NET_INCOME'!B49<0,ABS('💧 WATERFALL_NET_INCOME'!B49),0) -> 0 | E47: =0 -> 0 | G47: ='💧 WATERFALL_NET_INCOME'!A47 -> Net Interest Income | H47: ='💧 WATERFALL_NET_INCOME'!B47 -> 466 | J47: =J46+H47 -> 11441 | K47: =IF(H47>=0,J46,J47) -> 10975 | L47: =MAX(H47,0) -> 466 | M47: =MAX(-H47,0) -> 0 | N47: =0 -> 0
A48: Other NBI 23→24 | B48: =MIN('💧 WATERFALL_NET_INCOME'!C49,'💧 WATERFALL_NET_INCOME'!C50) -> 13544 | C48: =IF('💧 WATERFALL_NET_INCOME'!B50>0,ABS('💧 WATERFALL_NET_INCOME'!B50),0) -> 142 | D48: =IF('💧 WATERFALL_NET_INCOME'!B50<0,ABS('💧 WATERFALL_NET_INCOME'!B50),0) -> 0 | E48: =0 -> 0 | G48: ='💧 WATERFALL_NET_INCOME'!A48 -> Fee & Commission Income | H48: ='💧 WATERFALL_NET_INCOME'!B48 -> 880 | J48: =J47+H48 -> 12321 | K48: =IF(H48>=0,J47,J48) -> 11441 | L48: =MAX(H48,0) -> 880 | M48: =MAX(-H48,0) -> 0 | N48: =0 -> 0
A49: OpEx 23→24 | B49: =MIN('💧 WATERFALL_NET_INCOME'!C50,'💧 WATERFALL_NET_INCOME'!C51) -> 13686 | C49: =IF('💧 WATERFALL_NET_INCOME'!B51>0,ABS('💧 WATERFALL_NET_INCOME'!B51),0) -> 246 | D49: =IF('💧 WATERFALL_NET_INCOME'!B51<0,ABS('💧 WATERFALL_NET_INCOME'!B51),0) -> 0 | E49: =0 -> 0 | G49: ='💧 WATERFALL_NET_INCOME'!A49 -> Trading Income | H49: ='💧 WATERFALL_NET_INCOME'!B49 -> 1223 | J49: =J48+H49 -> 13544 | K49: =IF(H49>=0,J48,J49) -> 12321 | L49: =MAX(H49,0) -> 1223 | M49: =MAX(-H49,0) -> 0 | N49: =0 -> 0
A50: Cost of Risk 23→24 | B50: =MIN('💧 WATERFALL_NET_INCOME'!C51,'💧 WATERFALL_NET_INCOME'!C52) -> 13932 | C50: =IF('💧 WATERFALL_NET_INCOME'!B52>0,ABS('💧 WATERFALL_NET_INCOME'!B52),0) -> 763 | D50: =IF('💧 WATERFALL_NET_INCOME'!B52<0,ABS('💧 WATERFALL_NET_INCOME'!B52),0) -> 0 | E50: =0 -> 0 | G50: ='💧 WATERFALL_NET_INCOME'!A50 -> Other operating activities | H50: ='💧 WATERFALL_NET_INCOME'!B50 -> 142 | J50: =J49+H50 -> 13686 | K50: =IF(H50>=0,J49,J50) -> 13544 | L50: =MAX(H50,0) -> 142 | M50: =MAX(-H50,0) -> 0 | N50: =0 -> 0
A51: Non-op 23→24 | B51: =MIN('💧 WATERFALL_NET_INCOME'!C52,'💧 WATERFALL_NET_INCOME'!C53) -> 14603 | C51: =IF('💧 WATERFALL_NET_INCOME'!B53>0,ABS('💧 WATERFALL_NET_INCOME'!B53),0) -> 0 | D51: =IF('💧 WATERFALL_NET_INCOME'!B53<0,ABS('💧 WATERFALL_NET_INCOME'!B53),0) -> 92 | E51: =0 -> 0 | G51: ='💧 WATERFALL_NET_INCOME'!A51 -> Unallocated NBI components | H51: ='💧 WATERFALL_NET_INCOME'!B51 -> 246 | J51: =J50+H51 -> 13932 | K51: =IF(H51>=0,J50,J51) -> 13686 | L51: =MAX(H51,0) -> 246 | M51: =MAX(-H51,0) -> 0 | N51: =0 -> 0
A52: Tax 23→24 | B52: =MIN('💧 WATERFALL_NET_INCOME'!C53,'💧 WATERFALL_NET_INCOME'!C54) -> 14603 | C52: =IF('💧 WATERFALL_NET_INCOME'!B54>0,ABS('💧 WATERFALL_NET_INCOME'!B54),0) -> 573 | D52: =IF('💧 WATERFALL_NET_INCOME'!B54<0,ABS('💧 WATERFALL_NET_INCOME'!B54),0) -> 0 | E52: =0 -> 0 | G52: ='💧 WATERFALL_NET_INCOME'!A52 -> Operating expenses effect | H52: ='💧 WATERFALL_NET_INCOME'!B52 -> 763 | J52: =J51+H52 -> 14695 | K52: =IF(H52>=0,J51,J52) -> 13932 | L52: =MAX(H52,0) -> 763 | M52: =MAX(-H52,0) -> 0 | N52: =0 -> 0
A53: Disc. ops / NCI 23→24 | B53: =MIN('💧 WATERFALL_NET_INCOME'!C54,'💧 WATERFALL_NET_INCOME'!C55) -> 15176 | C53: =IF('💧 WATERFALL_NET_INCOME'!B55>0,ABS('💧 WATERFALL_NET_INCOME'!B55),0) -> 262 | D53: =IF('💧 WATERFALL_NET_INCOME'!B55<0,ABS('💧 WATERFALL_NET_INCOME'!B55),0) -> 0 | E53: =0 -> 0 | G53: ='💧 WATERFALL_NET_INCOME'!A53 -> Cost of Risk effect | H53: ='💧 WATERFALL_NET_INCOME'!B53 -> -92 | J53: =J52+H53 -> 14603 | K53: =IF(H53>=0,J52,J53) -> 14603 | L53: =MAX(H53,0) -> 0 | M53: =MAX(-H53,0) -> 92 | N53: =0 -> 0
A54: FY 2024 | B54: =0 -> 0 | C54: =0 -> 0 | D54: =0 -> 0 | E54: ='💧 WATERFALL_NET_INCOME'!B56 -> -735 | G54: ='💧 WATERFALL_NET_INCOME'!A54 -> Other net losses for risk on financial instruments effect | H54: ='💧 WATERFALL_NET_INCOME'!B54 -> 573 | J54: =J53+H54 -> 15176 | K54: =IF(H54>=0,J53,J54) -> 14603 | L54: =MAX(H54,0) -> 573 | M54: =MAX(-H54,0) -> 0 | N54: =0 -> 0
G55: ='💧 WATERFALL_NET_INCOME'!A55 -> Non-operating items | H55: ='💧 WATERFALL_NET_INCOME'!B55 -> 262 | J55: =J54+H55 -> 15438 | K55: =IF(H55>=0,J54,J55) -> 15176 | L55: =MAX(H55,0) -> 262 | M55: =MAX(-H55,0) -> 0 | N55: =0 -> 0
G56: ='💧 WATERFALL_NET_INCOME'!A56 -> Tax effect | H56: ='💧 WATERFALL_NET_INCOME'!B56 -> -735 | J56: =J55+H56 -> 14703 | K56: =IF(H56>=0,J55,J56) -> 14703 | L56: =MAX(H56,0) -> 0 | M56: =MAX(-H56,0) -> 735 | N56: =0 -> 0
G57: ='💧 WATERFALL_NET_INCOME'!A57 -> Discontinued operations & minority interests | H57: ='💧 WATERFALL_NET_INCOME'!B57 -> -3015 | J57: =J56+H57 -> 11688 | K57: =IF(H57>=0,J56,J57) -> 11688 | L57: =MAX(H57,0) -> 0 | M57: =MAX(-H57,0) -> 3015 | N57: =0 -> 0
G58: ='💧 WATERFALL_NET_INCOME'!A58 -> Closing net income FY2024 | H58: ='💧 WATERFALL_NET_INCOME'!B58 -> 11688 | J58: =H58 -> 11688 | K58: =0 -> 0 | L58: =0 -> 0 | M58: =0 -> 0 | N58: =H58 -> 11688

Sheet 🔍 CHECKS
A1: BNP PARIBAS — WORKBOOK INTEGRITY CHECKS
A2: FY 2022–FY 2024 | Financial audit and model-control register
A3: PASS = within tolerance or source-verified | REVIEW = unresolved exception | Most tests use live workbook formulas
A4: ="Control status is generated from the live control register below. "&IF(B35=0,"All controls pass.",B35&" control(s) require review before publication.") -> Control status is generated from the live control register below. All controls pass.
A6: CONTROL REGISTER
A7: CHECK | B7: DESCRIPTION | C7: TEST / EXPECTED CONDITION | D7: RESULT | E7: TOLERANCE / LIMIT | F7: STATUS | G7: SOURCE | H7: CONTROL OWNER | I7: VALIDATION METHOD | J7: LAST REVIEWED
A8: CHECK 01 | B8: Balance sheet FY2022 balances | C8: Total assets less liabilities and equity | D8: ='🏦 BALANCE_SHEET'!B68 -> 0 | E8: ±€1M | F8: =IF(ABS(D8)<=1,"PASS","REVIEW") -> PASS | G8: 🏦 BALANCE_SHEET!B68 | H8: Joy Lorna | I8: Formula reconciliation | J8: =DATE(2026,8,25) -> 46259
A9: CHECK 02 | B9: Balance sheet FY2023 balances | C9: Total assets less liabilities and equity | D9: ='🏦 BALANCE_SHEET'!C68 -> 0 | E9: ±€1M | F9: =IF(ABS(D9)<=1,"PASS","REVIEW") -> PASS | G9: 🏦 BALANCE_SHEET!C68 | H9: Joy Lorna | I9: Formula reconciliation | J9: =DATE(2026,8,25) -> 46259
A10: CHECK 03 | B10: Balance sheet FY2024 balances | C10: Total assets less liabilities and equity | D10: ='🏦 BALANCE_SHEET'!D68 -> 0 | E10: ±€1M | F10: =IF(ABS(D10)<=1,"PASS","REVIEW") -> PASS | G10: 🏦 BALANCE_SHEET!D68 | H10: Joy Lorna | I10: Formula reconciliation | J10: =DATE(2026,8,25) -> 46259
A11: CHECK 04 | B11: FY2022 cash-equivalent roll-forward reconciles | C11: Calculated closing less reported IAS 7 closing balance | D11: ='💰 CASH_FLOW'!B49 -> 0 | E11: €0M | F11: =IF(ABS(D11)<=1,"PASS","REVIEW") -> PASS | G11: 💰 CASH_FLOW!B49 | H11: Joy Lorna | I11: Cross-statement formula reconciliation | J11: =DATE(2026,8,25) -> 46259
A12: CHECK 05 | B12: FY2023 cash-equivalent roll-forward reconciles | C12: Calculated closing less reported IAS 7 closing balance | D12: ='💰 CASH_FLOW'!C49 -> 0 | E12: €0M | F12: =IF(ABS(D12)<=1,"PASS","REVIEW") -> PASS | G12: 💰 CASH_FLOW!C49 | H12: Joy Lorna | I12: Manual comparison to official FY2023 source | J12: =DATE(2026,8,25) -> 46259
A13: CHECK 06 | B13: FY2024 cash-equivalent roll-forward reconciles | C13: Calculated closing less reported IAS 7 closing balance | D13: ='💰 CASH_FLOW'!D49 -> 0 | E13: €0M | F13: =IF(ABS(D13)<=1,"PASS","REVIEW") -> PASS | G13: 💰 CASH_FLOW!D49 | H13: Joy Lorna | I13: Manual comparison to official FY2024 source | J13: =DATE(2026,8,25) -> 46259
A14: CHECK 07 | B14: Variance bridge FY2022→FY2023 reconciles | C14: Calculated close less source close | D14: ='🧮VARIANCE BRIDGE'!B21 -> 0 | E14: €0M | F14: =IF(ABS(D14)<=1,"PASS","REVIEW") -> PASS | G14: 🧮VARIANCE BRIDGE!B21 | H14: Joy Lorna | I14: Bridge formula reconciliation | J14: =DATE(2026,8,25) -> 46259
A15: CHECK 08 | B15: Variance bridge FY2023→FY2024 reconciles | C15: Calculated close less source close | D15: ='🧮VARIANCE BRIDGE'!B38 -> 0 | E15: €0M | F15: =IF(ABS(D15)<=1,"PASS","REVIEW") -> PASS | G15: 🧮VARIANCE BRIDGE!B38 | H15: Joy Lorna | I15: Bridge formula reconciliation | J15: =DATE(2026,8,25) -> 46259
A16: CHECK 09 | B16: Waterfall FY2022→FY2023 reconciles | C16: Calculated close less source close | D16: ='💧 WATERFALL_NET_INCOME'!F61 -> 0 | E16: €0M | F16: =IF(ABS(D16)<=1,"PASS","REVIEW") -> PASS | G16: 💧 WATERFALL_NET_INCOME!F61 | H16: Joy Lorna | I16: Waterfall formula reconciliation | J16: =DATE(2026,8,25) -> 46259
A17: CHECK 10 | B17: Waterfall FY2023→FY2024 reconciles | C17: Calculated close less source close | D17: ='💧 WATERFALL_NET_INCOME'!F62 -> 0 | E17: €0M | F17: =IF(ABS(D17)<=1,"PASS","REVIEW") -> PASS | G17: 💧 WATERFALL_NET_INCOME!F62 | H17: Joy Lorna | I17: Waterfall formula reconciliation | J17: =DATE(2026,8,25) -> 46259
A18: CHECK 11 | B18: CIR agrees between statement and ratio sheet | C18: Maximum absolute difference across three years | D18: =MAX(ABS('📄 INCOME_STATEMENT'!B48-'📈 RATIOS_EFFICIENCY'!C8),ABS('📄 INCOME_STATEMENT'!C48-'📈 RATIOS_EFFICIENCY'!D8),ABS('📄 INCOME_STATEMENT'!D48-'📈 RATIOS_EFFICIENCY'!E8)) -> 0 | E18: ≤0.01 pp | F18: =IF(ABS(D18)<=0.0001,"PASS","REVIEW") -> PASS | G18: 📄 INCOME_STATEMENT!B48:D48 vs 📈 RATIOS_EFFICIENCY!C8:E8 | H18: Joy Lorna | I18: Cross-sheet ratio agreement | J18: =DATE(2026,8,25) -> 46259
A19: CHECK 12 | B19: Net Income 2-Year CAGR (FY22–FY24) formula is valid | C19: Recalculated 2-year CAGR less profitability result | D19: =(('📄 INCOME_STATEMENT'!D44/'📄 INCOME_STATEMENT'!B44)^(1/2)-1)-'📈 RATIOS_PROFITABILITY'!E16 -> 0 | E19: ≤0.01 pp | F19: =IF(ABS(D19)<=0.0001,"PASS","REVIEW") -> PASS | G19: 📈 RATIOS_PROFITABILITY!E16 | H19: Joy Lorna | I19: Independent formula recalculation | J19: =DATE(2026,8,25) -> 46259
A20: CHECK 13 | B20: CET1 agrees between capital and summary sheets | C20: Maximum absolute difference | D20: =ABS('📈 RATIOS_CAPITAL'!E8-'📊 EXECUTIVE_SUMMARY'!D29) -> 0 | E20: ≤0.01 pp | F20: =IF(ABS(D20)<=0.0001,"PASS","REVIEW") -> PASS | G20: 📈 RATIOS_CAPITAL!E8 vs 📊 EXECUTIVE_SUMMARY!D29 | H20: Joy Lorna | I20: Cross-sheet ratio agreement | J20: =DATE(2026,8,25) -> 46259
A21: CHECK 14 | B21: LCR meets minimum in all years | C21: Minimum LCR less 100% | D21: =MIN('📈 RATIOS_LIQUIDITY'!C8:E8)-100% -> 0.29 | E21: ≥0 pp | F21: =IF(D21>0,"PASS","REVIEW") -> PASS | G21: 📈 RATIOS_LIQUIDITY!C8:E8 | H21: Joy Lorna | I21: Regulatory minimum comparison | J21: =DATE(2026,8,25) -> 46259
A22: CHECK 15 | B22: NSFR meets minimum in all years | C22: Minimum NSFR less 100% | D22: =MIN('📈 RATIOS_LIQUIDITY'!C9:E9)-100% -> 0.1175 | E22: ≥0 pp | F22: =IF(D22>0,"PASS","REVIEW") -> PASS | G22: 📈 RATIOS_LIQUIDITY!C9:E9 | H22: Joy Lorna | I22: Regulatory minimum comparison | J22: =DATE(2026,8,25) -> 46259
A23: CHECK 16 | B23: Loan-to-deposit remains below 100% | C23: 100% less maximum ratio | D23: =100%-MAX('📈 RATIOS_LIQUIDITY'!C11:E11) -> 0.13017837 | E23: >0 pp | F23: =IF(D23>0,"PASS","REVIEW") -> PASS | G23: 📈 RATIOS_LIQUIDITY!C11:E11 | H23: Joy Lorna | I23: Analytical funding comparison | J23: =DATE(2026,8,25) -> 46259
A24: CHECK 17 | B24: NPL remains below EU reference | C24: 2.3% less maximum NPL | D24: =2.3%-MAX('📈 RATIOS_ASSET_QUALITY'!C8:E8) -> 0.006 | E24: >0 pp | F24: =IF(D24>0,"PASS","REVIEW") -> PASS | G24: 📈 RATIOS_ASSET_QUALITY!C8:E8 | H24: Joy Lorna | I24: ECB 2024 Q2 sector-reference comparison | J24: =DATE(2026,8,25) -> 46259
A25: CHECK 18 | B25: FY2024 CIR is below 66% analytical comparison | C25: 66% comparison less FY2024 CIR | D25: =66%-'📈 RATIOS_EFFICIENCY'!E8 -> 0.041683766 | E25: >0 pp | F25: =IF(D25>0,"PASS","REVIEW") -> PASS | G25: 📈 RATIOS_EFFICIENCY!E8 | H25: Joy Lorna | I25: Internal analytical comparison | J25: =DATE(2026,8,25) -> 46259
A26: CHECK 19 | B26: Chart source NBI agrees to income statement | C26: Maximum absolute difference | D26: =MAX(ABS(🔗CHART_SOURCE!B7-'📄 INCOME_STATEMENT'!B15),ABS(🔗CHART_SOURCE!C7-'📄 INCOME_STATEMENT'!C15),ABS(🔗CHART_SOURCE!D7-'📄 INCOME_STATEMENT'!D15)) -> 0 | E26: €0M | F26: =IF(ABS(D26)<=1,"PASS","REVIEW") -> PASS | G26: 🔗CHART_SOURCE!B7:D7 | H26: Joy Lorna | I26: Cross-sheet chart-source agreement | J26: =DATE(2026,8,25) -> 46259
A27: CHECK 20 | B27: Chart source NPL agrees to asset-quality sheet | C27: Maximum absolute difference | D27: =MAX(ABS(🔗CHART_SOURCE!B22-'📈 RATIOS_ASSET_QUALITY'!C8),ABS(🔗CHART_SOURCE!C22-'📈 RATIOS_ASSET_QUALITY'!D8),ABS(🔗CHART_SOURCE!D22-'📈 RATIOS_ASSET_QUALITY'!E8)) -> 0 | E27: 0.00 pp | F27: =IF(ABS(D27)<=0.0001,"PASS","REVIEW") -> PASS | G27: 🔗CHART_SOURCE!B22:D22 | H27: Joy Lorna | I27: Cross-sheet chart-source agreement | J27: =DATE(2026,8,25) -> 46259
A28: CHECK 21 | B28: Source register required fields complete | C28: No blank metric, document, year, reference, workbook sheet, cell, URL, or evidence-status fields | D28: =COUNTBLANK(SOURCE_REGISTER!A7:I117) -> 0 | E28: 0 blanks | F28: =IF(D28=0,"PASS","REVIEW") -> PASS | G28: SOURCE_REGISTER!A7:I117 | H28: Joy Lorna | I28: Required-field completeness test | J28: =DATE(2026,8,25) -> 46259
A29: CHECK 22 | B29: Ratio and data dictionaries complete | C29: Required ratio count = 12 and required field count ≥ 8 | D29: =MIN(COUNTA(RATIO_DICTIONARY!A7:A18)-12,COUNTA(DATA_DICTIONARY!A7:A19)-8) -> 0 | E29: ≥0 | F29: =IF(D29>=0,"PASS","REVIEW") -> PASS | G29: RATIO_DICTIONARY and DATA_DICTIONARY | H29: Joy Lorna | I29: Required-entry count test | J29: =DATE(2026,8,25) -> 46259
A30: CHECK 23 | B30: IFRS 17 restatement calculations complete | C30: All difference and materiality cells populated | D30: =COUNTBLANK(IFRS17_RESTATEMENT_NOTE!D7:E10) -> 0 | E30: 0 blanks | F30: =IF(D30=0,"PASS","REVIEW") -> PASS | G30: IFRS17_RESTATEMENT_NOTE!D7:E10 | H30: Joy Lorna | I30: Formula-population test | J30: =DATE(2026,8,25) -> 46259
A33: CONTROL SUMMARY
A34: PASS COUNT | B34: REVIEW COUNT | C34: TOTAL CHECKS | D34: OVERALL STATUS
A35: =COUNTIF(F8:F30,"PASS") -> 23 | B35: =COUNTIF(F8:F30,"REVIEW") -> 0 | C35: =COUNTA(A8:A30) -> 23 | D35: =IF(B35=0,"READY","REVIEW REQUIRED") -> READY
A38: DATA SOURCE LOG
A39: FIGURE / AREA | B39: SOURCE DOCUMENT | C39: PAGE / SECTION | D39: WORKBOOK LOCATION
A40: NBI and Net Income FY2022 | B40: BNP Paribas FY2022 Results | C40: Consolidated P&L / Net income | D40: 📄 INCOME_STATEMENT
A41: NBI and Net Income FY2023 | B41: BNP Paribas FY2023 Results | C41: Consolidated P&L / Net income | D41: 📄 INCOME_STATEMENT
A42: NBI and Net Income FY2024 | B42: BNP Paribas FY2024 Results | C42: Consolidated P&L / Net income | D42: 📄 INCOME_STATEMENT
A43: Balance sheet totals | B43: BNP Paribas annual financial statements | C43: Consolidated balance sheet | D43: 🏦 BALANCE_SHEET
A44: Cash flow | B44: BNP Paribas annual financial statements | C44: Consolidated cash-flow statement | D44: 💰 CASH_FLOW
A45: ROE, ROTE and EPS | B45: BNP Paribas annual results | C45: Key indicators / per-share data | D45: 📈 RATIOS_PROFITABILITY
A46: CET1, Tier 1, Total Capital and RWA | B46: BNP Paribas Pillar 3 / annual results | C46: Capital adequacy tables | D46: 📈 RATIOS_CAPITAL
A47: LCR and NSFR | B47: BNP Paribas Pillar 3 reports | C47: Liquidity chapter | D47: 📈 RATIOS_LIQUIDITY
A48: NPL, Coverage and IFRS 9 allowances | B48: BNP Paribas Pillar 3 reports | C48: Credit-risk chapter | D48: 📈 RATIOS_ASSET_QUALITY
A49: CIR and Operating Leverage | B49: BNP Paribas annual results | C49: Operating efficiency metrics | D49: 📈 RATIOS_EFFICIENCY
A50: Trend and waterfall charts | B50: Linked workbook calculations | C50: Chart source schedules | D50: 🔗CHART_SOURCE

Sheet SOURCE_REGISTER
A1: BNP PARIBAS — SOURCE REGISTER
A2: Metric-level traceability for FY2022–FY2024 workbook figures
A4: Page-level references are recorded where confirmed in the official indexed document. Where the index exposes the metric and report section but not the printed page, the evidence status states this explicitly; no page number is inferred.
A6: Metric | B6: Source Document | C6: Year | D6: PAGE / EVIDENCE LOCATION | E6: Report Section | F6: Workbook Sheet | G6: Cell Reference | H6: SOURCE URL | I6: EVIDENCE STATUS
A7: FY2022 reported NBI | B7: FY2022 IFRS 17/9 restatement disclosure | C7: 2022 | D7: Restatement table | E7: Reported FY2022 series | F7: IFRS17_RESTATEMENT_NOTE | G7: B7 | H7: https://invest.bnpparibas/en/document/restatement-based-on-2023-format-of-2022-quarterly-series-pdf-file | I7: Figure verified in official restatement table
A8: FY2022 restated NBI | B8: FY2022 IFRS 17/9 restatement disclosure | C8: 2022 | D8: Restatement table | E8: Restated FY2022 series | F8: IFRS17_RESTATEMENT_NOTE | G8: C7 | H8: https://invest.bnpparibas/en/document/restatement-based-on-2023-format-of-2022-quarterly-series-pdf-file | I8: Figure verified in official restatement table
A9: FY2022 reported net income attributable to equity holders | B9: FY2022 IFRS 17/9 restatement disclosure | C9: 2022 | D9: Restatement table | E9: Reported FY2022 series | F9: IFRS17_RESTATEMENT_NOTE | G9: B9 | H9: https://invest.bnpparibas/en/document/restatement-based-on-2023-format-of-2022-quarterly-series-pdf-file | I9: Figure verified in official restatement table
A10: FY2022 restated net income attributable to equity holders | B10: FY2022 IFRS 17/9 restatement disclosure | C10: 2022 | D10: Restatement table | E10: Restated FY2022 series | F10: 📄 INCOME_STATEMENT | G10: B44 | H10: https://invest.bnpparibas/en/document/restatement-based-on-2023-format-of-2022-quarterly-series-pdf-file | I10: Figure verified in official restatement table
A11: FY2022 reported Cost of Risk | B11: FY2022 IFRS 17/9 restatement disclosure | C11: 2022 | D11: Restatement table | E11: Reported FY2022 series | F11: IFRS17_RESTATEMENT_NOTE | G11: B10 | H11: https://invest.bnpparibas/en/document/restatement-based-on-2023-format-of-2022-quarterly-series-pdf-file | I11: Figure verified in official restatement table
A12: FY2022 restated Cost of Risk | B12: FY2022 IFRS 17/9 restatement disclosure | C12: 2022 | D12: Restatement table | E12: Restated FY2022 series | F12: 📄 INCOME_STATEMENT | G12: B27 | H12: https://invest.bnpparibas/en/document/restatement-based-on-2023-format-of-2022-quarterly-series-pdf-file | I12: Figure verified in official restatement table
A13: Net Interest Income | B13: FY2022 restated comparative disclosure | C13: 2022 | D13: Restated results series | E13: Consolidated profit and loss account | F13: 📄 INCOME_STATEMENT | G13: B10 | H13: https://invest.bnpparibas/en/document/restatement-based-on-2023-format-of-2022-quarterly-series-pdf-file | I13: Section verified; printed page not assigned
A14: Net Interest Income | B14: FY2023 consolidated financial statements | C14: 2023 | D14: Consolidated profit and loss account | E14: Consolidated profit and loss account | F14: 📄 INCOME_STATEMENT | G14: C10 | H14: https://invest.bnpparibas/document/4q23-consolidated-financial-statements-annual-audited | I14: Section verified; printed page not assigned
A15: Net Interest Income | B15: FY2024 consolidated financial statements | C15: 2024 | D15: Consolidated profit and loss account | E15: Consolidated profit and loss account | F15: 📄 INCOME_STATEMENT | G15: D10 | H15: https://invest.bnpparibas/en/document/4q24-cfsu | I15: Section verified; printed page not assigned
A16: Net Fee & Commission Income | B16: FY2022 restated comparative disclosure | C16: 2022 | D16: Restated results series | E16: Consolidated profit and loss account | F16: 📄 INCOME_STATEMENT | G16: B11 | H16: https://invest.bnpparibas/en/document/restatement-based-on-2023-format-of-2022-quarterly-series-pdf-file | I16: Section verified; printed page not assigned
A17: Net Fee & Commission Income | B17: FY2023 consolidated financial statements | C17: 2023 | D17: Consolidated profit and loss account | E17: Consolidated profit and loss account | F17: 📄 INCOME_STATEMENT | G17: C11 | H17: https://invest.bnpparibas/document/4q23-consolidated-financial-statements-annual-audited | I17: Section verified; printed page not assigned
A18: Net Fee & Commission Income | B18: FY2024 consolidated financial statements | C18: 2024 | D18: Consolidated profit and loss account | E18: Consolidated profit and loss account | F18: 📄 INCOME_STATEMENT | G18: D11 | H18: https://invest.bnpparibas/en/document/4q24-cfsu | I18: Section verified; printed page not assigned
... A117: Closing cash and cash equivalents | B117: BNP Paribas 2024 Consolidated Financial Statements | C117: 2024 | D117: Cash flow statement — cash-equivalent accounts | E117: IAS 7 cash and cash equivalents reconciliation | F117: 💰 CASH_FLOW | G117: D48 | H117: https://invest.bnpparibas/en/document/4q24-cfsu | I117: Figure and component composition verified

Sheet IFRS17_RESTATEMENT_NOTE
A1: BNP PARIBAS — IFRS 17 / IFRS 9 RESTATEMENT NOTE
A2: Reported versus restated FY2022 key figures
A4: BNP Paribas adopted IFRS 17 and related insurance IFRS 9 changes from 1 January 2023 and presented selected FY2022 restated comparatives. This schedule documents the evidenced differences used to assess comparability.
A6: Line Item | B6: Reported FY2022 | C6: Restated FY2022 | D6: Difference | E6: Material to Analysis? | F6: Comments
A7: Revenues / NBI (€M) | B7: 50419 | C7: 45430 | D7: =C7-B7 -> -4989 | E7: =IF(ABS(D7)>=25,"Yes","No") -> Yes | F7: FY2022 reported revenues were €50,419M and restated revenues were €45,430M following the IFRS 17/9 presentation transition. Analytical comparisons use the restated figure.
A8: Gross Operating Income (€M) | B8: 15566 | C8: 15566 | D8: =C8-B8 -> 0 | E8: =IF(ABS(D8)>=25,"Yes","No") -> No | F8: No difference in the 2024 URD key-figures table.
A9: Net Income — Group Share (€M) | B9: 10196 | C9: 9848 | D9: =C9-B9 -> -348 | E9: =IF(ABS(D9)>=25,"Yes","No") -> Yes | F9: Restated FY2022 net income is €348M lower than reported. The analytical cross-year series uses the restated €9,848M baseline.
A10: Cost of Risk (€M) | B10: 2965 | C10: 3003 | D10: =C10-B10 -> 38 | E10: =IF(ABS(D10)>=25,"Yes","No") -> Yes | F10: Reported versus IFRS 17/9 restated comparative basis.
A12: Sources: BNP Paribas FY2022 IFRS 17/9 restatement disclosure and the Universal Registration Document and Annual Financial Report 2024 key-figures section. Only explicitly evidenced restatements are included.

Sheet RATIO_DICTIONARY
A1: BNP PARIBAS — RATIO DICTIONARY
A2: Definitions and interpretation for core banking ratios
A4: Definitions support interview defence and consistent interpretation. Regulatory ratios are distinguished from management or analytical measures.
A6: Ratio | B6: Formula | C6: Interpretation | D6: Source | E6: Notes
A7: ROE | B7: Net income — group share / average total equity | C7: Shareholder return generated from average equity. | D7: BNP annual results / analytical calculation | E7: Average-balance methodology; not a regulatory ratio.
A8: ROTE | B8: Net income — group share / average tangible equity | C8: Return generated on equity excluding goodwill and intangibles. | D8: BNP annual results / analytical calculation | E8: Definitions can differ between issuers; use consistently.
A9: ROA | B9: Net income — group share / average total assets | C9: Profitability relative to the balance-sheet asset base. | D9: Analytical calculation from financial statements | E9: Low absolute percentages are normal for banks.
A10: NIM | B10: Net interest income / average earning assets | C10: Yield spread earned on interest-bearing assets after funding cost. | D10: BNP financial statements / analytical calculation | E10: Sensitive to earning-asset definition and average balances.
A11: CIR | B11: Operating expenses / net banking income | C11: Cost efficiency; lower is generally better. | D11: BNP annual results / analytical calculation | E11: Workbook 66% level is an analytical comparison, not a rule.
A12: Cost of Risk | B12: BNP-reported Cost of Risk for the period / relevant average exposure basis, expressed in basis points | C12: Credit loss charge expressed in basis points. | D12: BNP annual results | E12: Use BNP’s published Cost of Risk metric; do not combine it with Other net losses for risk on financial instruments.
A13: LCR | B13: High-quality liquid assets / 30-day stressed net cash outflows | C13: Short-term liquidity resilience under stress. | D13: CRR Article 412 / LCR Delegated Act | E13: Regulatory minimum 100%.
A14: NSFR | B14: Available stable funding / required stable funding | C14: Structural funding resilience over a one-year horizon. | D14: CRR2 / BNP Pillar 3 | E14: Regulatory minimum 100%.
A15: CET1 | B15: CET1 capital / risk-weighted assets | C15: Highest-quality regulatory capital relative to risk exposure. | D15: CRR / BNP Pillar 3 | E15: No BNP-specific SREP threshold is asserted in this workbook.
A16: Leverage Ratio | B16: Tier 1 capital / total exposure measure | C16: Non-risk-based capital backstop. | D16: CRR / BNP Pillar 3 | E16: 3% regulatory reference floor used for comparison.
A17: NPL Ratio | B17: Non-performing loans / gross loans and advances | C17: Share of lending classified as non-performing. | D17: EBA definition / BNP credit-risk disclosure | E17: Compare definitions before peer analysis.
A18: Coverage Ratio | B18: Stage 3 allowances / gross Stage 3 exposure | C18: Loss-absorption buffer against non-performing exposures. | D18: BNP credit-risk disclosure | E18: Collateral practices affect cross-bank comparability.

Sheet DATA_DICTIONARY
A1: BNP PARIBAS — DATA DICTIONARY
A2: Definitions, units, and source families for core fields
A4: This dictionary standardises banking terminology used throughout the financial statements, ratio schedules, charts, and controls.
A6: Field | B6: Definition | C6: Unit | D6: Source | E6: Comments
A7: NBI | B7: Net banking income: operating revenue after netting interest, fees, trading, and other banking activities. | C7: €M | D7: BNP consolidated income statement | E7: Banking equivalent of top-line operating revenue.
A8: NII | B8: Net interest income earned from interest-bearing assets less interest expense. | C8: €M | D8: BNP consolidated income statement | E8: Distinct from NIM, which is a ratio.
A9: HQLA | B9: High-quality liquid assets eligible for the liquidity buffer. | C9: €M | D9: BNP Pillar 3 liquidity disclosure | E9: Predominantly Level 1 assets.
A10: RWA | B10: Risk-weighted assets used as the denominator for risk-based capital ratios. | C10: €M | D10: BNP Pillar 3 capital disclosure | E10: Includes credit, market, and operational risk.
A11: CET1 | B11: Common Equity Tier 1 capital, the highest-quality regulatory capital. | C11: €M / % | D11: BNP Pillar 3 capital disclosure | E11: Amount when in €M; ratio when divided by RWA.
A12: Stage 1 ECL | B12: 12-month expected credit loss on performing exposures without significant credit deterioration. | C12: €M | D12: BNP IFRS 9 credit-risk disclosure | E12: Performing book allowance.
A13: Stage 2 ECL | B13: Lifetime expected credit loss on exposures with significant increase in credit risk. | C13: €M | D13: BNP IFRS 9 credit-risk disclosure | E13: Migration is an early-warning indicator.
A14: Stage 3 ECL | B14: Allowance on credit-impaired or non-performing exposures. | C14: €M | D14: BNP IFRS 9 credit-risk disclosure | E14: Used in coverage analysis.
A15: LCR | B15: Liquidity coverage ratio for a 30-day stress horizon. | C15: % | D15: BNP Pillar 3 liquidity disclosure | E15: Minimum 100%.
A16: NSFR | B16: Net stable funding ratio over a one-year horizon. | C16: % | D16: BNP Pillar 3 liquidity disclosure | E16: Minimum 100%.
A17: Cost of Risk | B17: BNP-reported credit-risk impairment charge for intermediation activities. | C17: €M / bps | D17: BNP consolidated income statement / results | E17: Kept separate from other net risk losses.
... A19: Total risk-related charges | B19: Cost of Risk plus other net losses for risk on financial instruments. | C19: €M | D19: Analytical calculation | E19: Used only when explicitly labelled as combined charges.

Sheet BENCHMARKS
A1: BNP PARIBAS — ASSUMPTIONS & BENCHMARKS
A2: Central register of external sector references and analytical comparisons
A4: Benchmarks are comparison points, not BNP-specific requirements or forecasts. No SREP threshold is inferred unless directly evidenced by a supervisory disclosure.
A6: Measure | B6: Benchmark | C6: Source | D6: Date | E6: Notes
A7: ROE | B7: 0.1011 | C7: ECB Supervisory Banking Statistics — significant institutions | D7: 2024 Q2 | E7: Sector aggregate; comparison only.
A8: NIM | B8: 0.0161 | C8: ECB Supervisory Banking Statistics — significant institutions | D8: 2024 Q2 | E8: Sector aggregate; country mix varies.
A9: NPL Ratio | B9: 0.023 | C9: ECB Supervisory Banking Statistics — significant institutions | D9: 2024 Q2 | E9: Excludes cash balances and other demand deposits.
A10: CET1 Ratio | B10: 0.1581 | C10: ECB Supervisory Banking Statistics — significant institutions | D10: 2024 Q2 | E10: Sector aggregate; not BNP’s requirement.
A11: Cost of Risk | B11: 47 | C11: ECB Supervisory Banking Statistics — significant institutions | D11: 2024 Q2 | E11: Basis points; sector aggregate.
A12: ROE | B12: 0.111 | C12: EBA Risk Dashboard — EU/EEA banks | D12: 2024 Q3 | E12: Sample aggregate; comparison only.
A13: NIM | B13: 0.0166 | C13: EBA Risk Dashboard — EU/EEA banks | D13: 2024 Q3 | E13: Sample aggregate.
A14: NPL Ratio | B14: 0.0188 | C14: EBA Risk Dashboard — EU/EEA banks | D14: 2024 Q3 | E14: Sample aggregate.
A15: CET1 Ratio | B15: 0.16 | C15: EBA Risk Dashboard — EU/EEA banks | D15: 2024 Q3 | E15: Fully loaded aggregate.
A16: LCR | B16: 1.614 | C16: EBA Risk Dashboard — EU/EEA banks | D16: 2024 Q3 | E16: Sector aggregate; regulatory minimum remains 100%.
A17: NSFR | B17: 1.272 | C17: EBA Risk Dashboard — EU/EEA banks | D17: 2024 Q3 | E17: Sector aggregate; regulatory minimum remains 100%.
A18: Cost-to-Income Ratio | B18: 0.66 | C18: Internal analytical comparison | D18: FY2024 review | E18: Not a regulatory requirement or external target.
A19: CET1 SREP threshold | B19: Not asserted | C19: No evidenced BNP-specific supervisory disclosure in workbook | D19: As reviewed 2026-08-25 | E19: Regulatory reference levels used for analytical comparison only.

Sheet WORKBOOK_METHODOLOGY
A1: BNP PARIBAS — WORKBOOK METHODOLOGY
A2: Scope, data collection, analytical approach, and limitations
A4: This one-page methodology defines what the workbook covers, how figures were collected, and what conclusions should not be drawn from the analysis.
A6: Methodology Area | B6: Workbook Approach
A7: Scope | B7: BNP Paribas SA consolidated Group; not a standalone review of BGL BNP Paribas SA.
A8: Years | B8: FY2022–FY2024
A9: Accounting Framework | B9: IFRS as adopted by the European Union. FY2022 uses IFRS 17/9 restated comparative figures where applicable to maintain comparability with FY2023–FY2024.
A10: Currency | B10: EUR millions unless stated otherwise.
A11: Data Collection | B11: Manual extraction from official BNP Paribas annual reports, results releases, slides, and Pillar 3 disclosures.
A12: Analysis Type | B12: Historical financial-statement analysis, ratio analysis, variance bridges, and control checks.
A13: Validation | B13: Live formula reconciliations plus source-document comparison; see SOURCE_REGISTER and 🔍 CHECKS.
A14: Entity Relevance | B14: Selected for Luxembourg relevance through BNP Paribas Group operations including BGL BNP Paribas; analysis remains Group-consolidated.
A15: Accounting Basis Methodology | B15: FY2022 operating and comparative figures affected by IFRS 17/9 use BNP Paribas’ restated disclosures. Reported and restated values are retained separately in IFRS17_RESTATEMENT_NOTE; the analytical series uses the consistent restated basis where required.
A17: LIMITATIONS
A18: 1 | B18: Annual data only
A19: 2 | B19: No forecasts or consensus estimates
A20: 3 | B20: No valuation analysis
A21: 4 | B21: No stress testing
A22: 5 | B22: FY2022 comparatives follow BNP’s disclosed restatement perimeter. IAS 7 cash and cash equivalents are reconciled separately from the balance-sheet central-bank cash line using the published component composition.

Sheet ANALYTICAL_INPUTS
A1: BNP PARIBAS — ANALYTICAL INPUTS
A2: Visible denominator inputs supporting ROE, ROTE, ROA, and NIM calculations
A4: AVERAGE-BALANCE DENOMINATORS
A6: Metric | B6: Period | C6: Value | D6: Unit | E6: Source | F6: Page / Section | G6: Purpose | H6: Source URL
A7: Average total equity | B7: FY2022 | C7: 119561.5 | D7: €M | E7: BNP Paribas FY2022 annual report | F7: Consolidated balance sheet — opening and closing total equity | G7: ROE denominator | H7: https://invest.bnpparibas/en/document/universal-registration-document-2022
A8: Average total equity | B8: FY2023 | C8: 122489.5 | D8: €M | E8: BNP Paribas FY2023 annual report | F8: Consolidated balance sheet — opening and closing total equity | G8: ROE denominator | H8: https://invest.bnpparibas/en/document/universal-registration-document-annual-financial-report-2023-pdf
A9: Average total equity | B9: FY2024 | C9: 125939.5 | D9: €M | E9: BNP Paribas FY2024 annual report | F9: Consolidated balance sheet — opening and closing total equity | G9: ROE denominator | H9: https://invest.bnpparibas/en/document/universal-registration-document-annual-financial-report-2024-pdf
A10: Average tangible equity | B10: FY2022 | C10: 110629.5 | D10: €M | E10: BNP Paribas FY2022 annual report | F10: Equity less goodwill and intangible assets — analytical average | G10: ROTE denominator | H10: https://invest.bnpparibas/en/document/universal-registration-document-2022
A11: Average tangible equity | B11: FY2023 | C11: 113102 | D11: €M | E11: BNP Paribas FY2023 annual report | F11: Equity less goodwill and intangible assets — analytical average | G11: ROTE denominator | H11: https://invest.bnpparibas/en/document/universal-registration-document-annual-financial-report-2023-pdf
A12: Average tangible equity | B12: FY2024 | C12: 116123 | D12: €M | E12: BNP Paribas FY2024 annual report | F12: Equity less goodwill and intangible assets — analytical average | G12: ROTE denominator | H12: https://invest.bnpparibas/en/document/universal-registration-document-annual-financial-report-2024-pdf
A13: Average total assets | B13: FY2022 | C13: 2649096 | D13: €M | E13: BNP Paribas FY2022 annual report | F13: Consolidated balance sheet — opening and closing total assets | G13: ROA denominator | H13: https://invest.bnpparibas/en/document/universal-registration-document-2022
A14: Average total assets | B14: FY2023 | C14: 2627623.5 | D14: €M | E14: BNP Paribas FY2023 annual report | F14: Consolidated balance sheet — opening and closing total assets | G14: ROA denominator | H14: https://invest.bnpparibas/en/document/universal-registration-document-annual-financial-report-2023-pdf
A15: Average total assets | B15: FY2024 | C15: 2648203.5 | D15: €M | E15: BNP Paribas FY2024 annual report | F15: Consolidated balance sheet — opening and closing total assets | G15: ROA denominator | H15: https://invest.bnpparibas/en/document/universal-registration-document-annual-financial-report-2024-pdf
A16: Average earning assets | B16: FY2022 | C16: 1011347.5 | D16: €M | E16: BNP Paribas FY2022 annual report | F16: Customer and bank loans plus debt securities — analytical average | G16: NIM denominator | H16: https://invest.bnpparibas/en/document/universal-registration-document-2022
A17: Average earning assets | B17: FY2023 | C17: 1047249 | D17: €M | E17: BNP Paribas FY2023 annual report | F17: Customer and bank loans plus debt securities — analytical average | G17: NIM denominator | H17: https://invest.bnpparibas/en/document/universal-registration-document-annual-financial-report-2023-pdf
A18: Average earning assets | B18: FY2024 | C18: 1102331.5 | D18: €M | E18: BNP Paribas FY2024 annual report | F18: Customer and bank loans plus debt securities — analytical average | G18: NIM denominator | H18: https://invest.bnpparibas/en/document/universal-registration-document-annual-financial-report-2024-pdf
A20: CONTROL NOTE
A21: Values reproduce the denominator assumptions previously embedded in profitability formulas. Sources identify the annual-report balance-sheet sections used for opening/closing balances; the analytical average and tangible/earning-asset transformations are now visible and reviewable.
